Workbook

Sheet Dashboard
A1: ⚙ SIMULADOR DPO — CAPACIDAD DE ALMACÉN 2026
A3: SUCURSAL | C3: ESCENARIO VENTA | E3: AÑO | G3: ← Clic en celda amarilla → lista desplegable | % picking y controladores: editar en Tablas_Operativas
A4: Casa Central | C4: 0.1 | E4: 2026 | G4: 💡 Cambiar Sucursal (A4) · Escenario (C4) · Año (E4) → todo se recalcula. Lógica diaria: ROUNDUP(Volumen/día ÷ productividad ÷ hs_día)
A6: ⚡ DECISIÓN: | B6: =IF(MIN(M17:M28)<-2,"🔴 BRECHA CRÍTICA — Peor mes: "&INDEX(A17:A28,MATCH(MIN(M17:M28),M17:M28,0))&" — faltan "&ABS(MIN(M17:M28))&" pickers. Contratar urgente.",IF(MIN(M17:M28)<0,"⚠ FALTAN PICKERS — Peor mes: "&INDEX(A17:A28,MATCH(MIN(M17:M28),M17:M28,0))&" — faltan "&ABS(MIN(M17:M28))&" persona(s).",IF(COUNTIF(P17:P28,"<0")>0,"⚠ BRECHA MHE — hay meses sin autoelevadores suficientes.","✅ CAPACIDAD OK con escenario "&TEXT(C4,"+0%;-0%;0%")&". Pickers suficientes todo el año."))) -> ✅ CAPACIDAD OK con escenario +10%. Pickers suficientes todo el año.
A8: BULTOS TOTALES AÑO | D8: HL TOTALES AÑO | G8: OP. PRESUPUESTADOS PROM. | J8: POOL PICKERS PROM. | M8: PICKERS NECES. PROM.
A9: =SUM(C17:C28) -> 1008980.5 | D9: =SUM(E17:E28) -> 94090.7 | G9: =IFERROR(AVERAGE(F17:F28),0) -> 9.0833333 | J9: =IFERROR(AVERAGE(K17:K28),0) -> 4.1666667 | M9: =IFERROR(AVERAGE(L17:L28),0) -> 1.9166667
A11: BRECHA PICKING PEOR MES | D11: MESES CON BRECHA | G11: AUTOS MÁX. REQUERIDOS | J11: % UTILIZACIÓN PROM. | M11: DÍAS TRAB. PROM.
A12: =IFERROR(MIN(M17:M28),0) -> 1 | D12: =COUNTIF(M17:M28,"<0") -> 0 | G12: =IFERROR(MAX(N17:N28),0) -> 4 | J12: =IFERROR(AVERAGE(U17:U28),0) -> 0.49586835 | M12: =IFERROR(AVERAGE(T17:T28),0) -> 26.083333
A14: 📋 CASCADA DIARIA: Presup → −Aus% → −Ctrl → −Autoelevadoristas → −Clasif.Vacíos → Pool Pickers → ¿Alcanzan? | Lógica: ROUNDUP(Volumen/día ÷ productividad ÷ hs.efectivas/día)
A15: MES | B15: VOLUMEN | D15: HL / AUTO | F15: PRESUP. | G15: DISP. NETO | H15: −CTRL. | I15: −AUTO ELEV. | J15: −CLASIF. VAC. | K15: POOL PICK. | L15: PICK. NECES. | M15: BRECHA PICK. | N15: AUTO REQ. | O15: AUTO DISP. | P15: BRECHA MHE | Q15: HS/DÍA POR TAREA | T15: % PICK | U15: % UTIL. | V15: ESTADO / DECISIÓN
A16: MES | B16: BULTOS BASE | C16: BULTOS AJUST. | D16: HL BASE | E16: HL AJUST. | F16: OP. PRESUP. | G16: OP. DISP. NETO | H16: − CONTROL. | I16: − AUTO ELEV. | J16: − CLASIF. VACÍOS | K16: POOL PICKERS | L16: PICKERS NECES. | M16: BRECHA PICKING | N16: AUTO REQ./DÍA | O16: AUTO DISP. | P16: BRECHA MHE | Q16: HS AUTO /DÍA | R16: HS CLASIF /DÍA | S16: HS PICK /DÍA | T16: % PICK | U16: % UTIL. | V16: ESTADO / DECISIÓN
A17: Enero | B17: =IFERROR(IF(SUMIFS(Datos_Volumen!$E:$E,Datos_Volumen!$A:$A,$A$4,Datos_Volumen!$B:$B,$E$4,Datos_Volumen!$C:$C,1)>0,SUMIFS(Datos_Volumen!$E:$E,Datos_Volumen!$A:$A,$A$4,Datos_Volumen!$B:$B,$E$4,Datos_Volumen!$C:$C,1),SUMIFS(Datos_Volumen!$E:$E,Datos_Volumen!$A:$A,$A$4,Datos_Volumen!$B:$B,$E$4-1,Datos_Volumen!$C:$C,1)),0) -> 252960 | C17: =B17*(1+$C$4) -> 278256 | D17: =IFERROR(IF(SUMIFS(Datos_Volumen!$F:$F,Datos_Volumen!$A:$A,$A$4,Datos_Volumen!$B:$B,$E$4,Datos_Volumen!$C:$C,1)>0,SUMIFS(Datos_Volumen!$F:$F,Datos_Volumen!$A:$A,$A$4,Datos_Volumen!$B:$B,$E$4,Datos_Volumen!$C:$C,1),SUMIFS(Datos_Volumen!$F:$F,Datos_Volumen!$A:$A,$A$4,Datos_Volumen!$B:$B,$E$4-1,Datos_Volumen!$C:$C,1)),0) -> 22766 | E17: =D17*(1+$C$4) -> 25042.6 | F17: =IFERROR(SUMIFS(Datos_Dotacion!$I:$I,Datos_Dotacion!$A:$A,$A$4,Datos_Dotacion!$B:$B,$E$4,Datos_Dotacion!$C:$C,1),0) -> 18 | G17: =FLOOR(F17*(1-(IFERROR(SUMIFS(Datos_Dotacion!$J:$J,Datos_Dotacion!$A:$A,$A$4,Datos_Dotacion!$B:$B,$E$4,Datos_Dotacion!$C:$C,1),0))),1) -> 17 | H17: =IF($A$4="Casa Central",Tablas_Operativas!B22,Tablas_Operativas!F22) -> 2 | I17: =IFERROR(ROUNDUP((E17/T17/Parametros!$B$7)/Parametros!$B$14,0),0) -> 4 | J17: =IFERROR(ROUNDUP(((IF((IFERROR(SUMIFS(Datos_Vacios!$G:$G,Datos_Vacios!$A:$A,$A$4,Datos_Vacios!$B:$B,$E$4,Datos_Vacios!$C:$C,1,Datos_Vacios!$F:$F,"Sí"),0))>0,(IFERROR(SUMIFS(Datos_Vacios!$G:$G,Datos_Vacios!$A:$A,$A$4,Datos_Vacios!$B:$B,$E$4,Datos_Vacios!$C:$C,1,Datos_Vacios!$F:$F,"Sí"),0)),(IFERROR(SUMIFS(Datos_Vacios!$G:$G,Datos_Vacios!$A:$A,$A$4,Datos_Vacios!$B:$B,$E$4-1,Datos_Vacios!$C:$C,1,Datos_Vacios!$F:$F,"Sí"),0))))*(1+$C$4)/T17/Parametros!$B$8)/Parametros!$B$14,0),0) -> 1 | K17: =MAX(G17-H17-I17-J17,0) -> 10 | L17: =IFERROR(ROUNDUP((C17*(IF($A$4="Casa Central",Tablas_Operativas!B6,Tablas_Operativas!F6))/T17/Parametros!$B$6)/Parametros!$B$16,0),0) -> 5 | M17: =K17-L17 -> 5 | N17: =I17 -> 4 | O17: =IFERROR(SUMIFS(Datos_Dotacion!$K:$K,Datos_Dotacion!$A:$A,$A$4,Datos_Dotacion!$B:$B,$E$4,Datos_Dotacion!$C:$C,1)+SUMIFS(Datos_Dotacion!$L:$L,Datos_Dotacion!$A:$A,$A$4,Datos_Dotacion!$B:$B,$E$4,Datos_Dotacion!$C:$C,1),0) -> 4 | P17: =O17-N17 -> 0 | Q17: =IFERROR(E17/T17/Parametros!$B$7,0) -> 21.07963 | R17: =IFERROR((IF((IFERROR(SUMIFS(Datos_Vacios!$G:$G,Datos_Vacios!$A:$A,$A$4,Datos_Vacios!$B:$B,$E$4,Datos_Vacios!$C:$C,1,Datos_Vacios!$F:$F,"Sí"),0))>0,(IFERROR(SUMIFS(Datos_Vacios!$G:$G,Datos_Vacios!$A:$A,$A$4,Datos_Vacios!$B:$B,$E$4,Datos_Vacios!$C:$C,1,Datos_Vacios!$F:$F,"Sí"),0)),(IFERROR(SUMIFS(Datos_Vacios!$G:$G,Datos_Vacios!$A:$A,$A$4,Datos_Vacios!$B:$B,$E$4-1,Datos_Vacios!$C:$C,1,Datos_Vacios!$F:$F,"Sí"),0))))*(1+$C$4)/T17/Parametros!$B$8,0) -> 6.1473251 | S17: =IFERROR(C17*(IF($A$4="Casa Central",Tablas_Operativas!B6,Tablas_Operativas!F6))/T17/Parametros!$B$6,0) -> 24.983704 | T17: =DAY(EOMONTH(DATE($E$4,1,1),0))-SUMPRODUCT((WEEKDAY(DATE($E$4,1,ROW(INDIRECT("1:"&DAY(EOMONTH(DATE($E$4,1,1),0))))),2)=7)*1) -> 27 | U17: =IFERROR((I17*Parametros!$B$14 + J17*Parametros!$B$14 + L17*Parametros!$B$16)/(G17*Parametros!$B$14),0) -> 0.50420168 | V17: =IF(M17<-2,"🔴 CRÍTICO — Contratar "&ABS(M17)&" pickers urgente",IF(M17<0,"🟠 FALTAN "&ABS(M17)&" picker(s) — horas extra o temp.",IF(P17<0,"🟡 FALTAN "&ABS(P17)&" auto(s) — evaluar alquiler",IF(U17>Parametros!$B$13,"🔴 SOBRECARGA "&TEXT(U17,"0%"),IF(U17>Parametros!$B$12,"🟡 RIESGO "&TEXT(U17,"0%"),IF(M17>3,"🟢 OK — evaluar reducir "&(M17-2)&" temp.","🟢 OK")))))) -> 🟢 OK — evaluar reducir 3 temp.
A18: Febrero | B18: =IFERROR(IF(SUMIFS(Datos_Volumen!$E:$E,Datos_Volumen!$A:$A,$A$4,Datos_Volumen!$B:$B,$E$4,Datos_Volumen!$C:$C,2)>0,SUMIFS(Datos_Volumen!$E:$E,Datos_Volumen!$A:$A,$A$4,Datos_Volumen!$B:$B,$E$4,Datos_Volumen!$C:$C,2),SUMIFS(Datos_Volumen!$E:$E,Datos_Volumen!$A:$A,$A$4,Datos_Volumen!$B:$B,$E$4-1,Datos_Volumen!$C:$C,2)),0) -> 177249 | C18: =B18*(1+$C$4) -> 194973.9 | D18: =IFERROR(IF(SUMIFS(Datos_Volumen!$F:$F,Datos_Volumen!$A:$A,$A$4,Datos_Volumen!$B:$B,$E$4,Datos_Volumen!$C:$C,2)>0,SUMIFS(Datos_Volumen!$F:$F,Datos_Volumen!$A:$A,$A$4,Datos_Volumen!$B:$B,$E$4,Datos_Volumen!$C:$C,2),SUMIFS(Datos_Volumen!$F:$F,Datos_Volumen!$A:$A,$A$4,Datos_Volumen!$B:$B,$E$4-1,Datos_Volumen!$C:$C,2)),0) -> 15895 | E18: =D18*(1+$C$4) -> 17484.5 | F18: =IFERROR(SUMIFS(Datos_Dotacion!$I:$I,Datos_Dotacion!$A:$A,$A$4,Datos_Dotacion!$B:$B,$E$4,Datos_Dotacion!$C:$C,2),0) -> 18 | G18: =FLOOR(F18*(1-(IFERROR(SUMIFS(Datos_Dotacion!$J:$J,Datos_Dotacion!$A:$A,$A$4,Datos_Dotacion!$B:$B,$E$4,Datos_Dotacion!$C:$C,2),0))),1) -> 17 | H18: =IF($A$4="Casa Central",Tablas_Operativas!B23,Tablas_Operativas!F23) -> 2 | I18: =IFERROR(ROUNDUP((E18/T18/Parametros!$B$7)/Parametros!$B$14,0),0) -> 3 | J18: =IFERROR(ROUNDUP(((IF((IFERROR(SUMIFS(Datos_Vacios!$G:$G,Datos_Vacios!$A:$A,$A$4,Datos_Vacios!$B:$B,$E$4,Datos_Vacios!$C:$C,2,Datos_Vacios!$F:$F,"Sí"),0))>0,(IFERROR(SUMIFS(Datos_Vacios!$G:$G,Datos_Vacios!$A:$A,$A$4,Datos_Vacios!$B:$B,$E$4,Datos_Vacios!$C:$C,2,Datos_Vacios!$F:$F,"Sí"),0)),(IFERROR(SUMIFS(Datos_Vacios!$G:$G,Datos_Vacios!$A:$A,$A$4,Datos_Vacios!$B:$B,$E$4-1,Datos_Vacios!$C:$C,2,Datos_Vacios!$F:$F,"Sí"),0))))*(1+$C$4)/T18/Parametros!$B$8)/Parametros!$B$14,0),0) -> 1 | K18: =MAX(G18-H18-I18-J18,0) -> 11 | L18: =IFERROR(ROUNDUP((C18*(IF($A$4="Casa Central",Tablas_Operativas!B7,Tablas_Operativas!F7))/T18/Parametros!$B$6)/Parametros!$B$16,0),0) -> 4 | M18: =K18-L18 -> 7 | N18: =I18 -> 3 | O18: =IFERROR(SUMIFS(Datos_Dotacion!$K:$K,Datos_Dotacion!$A:$A,$A$4,Datos_Dotacion!$B:$B,$E$4,Datos_Dotacion!$C:$C,2)+SUMIFS(Datos_Dotacion!$L:$L,Datos_Dotacion!$A:$A,$A$4,Datos_Dotacion!$B:$B,$E$4,Datos_Dotacion!$C:$C,2),0) -> 4 | P18: =O18-N18 -> 1 | Q18: =IFERROR(E18/T18/Parametros!$B$7,0) -> 16.557292 | R18: =IFERROR((IF((IFERROR(SUMIFS(Datos_Vacios!$G:$G,Datos_Vacios!$A:$A,$A$4,Datos_Vacios!$B:$B,$E$4,Datos_Vacios!$C:$C,2,Datos_Vacios!$F:$F,"Sí"),0))>0,(IFERROR(SUMIFS(Datos_Vacios!$G:$G,Datos_Vacios!$A:$A,$A$4,Datos_Vacios!$B:$B,$E$4,Datos_Vacios!$C:$C,2,Datos_Vacios!$F:$F,"Sí"),0)),(IFERROR(SUMIFS(Datos_Vacios!$G:$G,Datos_Vacios!$A:$A,$A$4,Datos_Vacios!$B:$B,$E$4-1,Datos_Vacios!$C:$C,2,Datos_Vacios!$F:$F,"Sí"),0))))*(1+$C$4)/T18/Parametros!$B$8,0) -> 4.9703704 | S18: =IFERROR(C18*(IF($A$4="Casa Central",Tablas_Operativas!B7,Tablas_Operativas!F7))/T18/Parametros!$B$6,0) -> 19.694333 | T18: =DAY(EOMONTH(DATE($E$4,2,1),0))-SUMPRODUCT((WEEKDAY(DATE($E$4,2,ROW(INDIRECT("1:"&DAY(EOMONTH(DATE($E$4,2,1),0))))),2)=7)*1) -> 24 | U18: =IFERROR((I18*Parametros!$B$14 + J18*Parametros!$B$14 + L18*Parametros!$B$16)/(G18*Parametros!$B$14),0) -> 0.40336134 | V18: =IF(M18<-2,"🔴 CRÍTICO — Contratar "&ABS(M18)&" pickers urgente",IF(M18<0,"🟠 FALTAN "&ABS(M18)&" picker(s) — horas extra o temp.",IF(P18<0,"🟡 FALTAN "&ABS(P18)&" auto(s) — evaluar alquiler",IF(U18>Parametros!$B$13,"🔴 SOBRECARGA "&TEXT(U18,"0%"),IF(U18>Parametros!$B$12,"🟡 RIESGO "&TEXT(U18,"0%"),IF(M18>3,"🟢 OK — evaluar reducir "&(M18-2)&" temp.","🟢 OK")))))) -> 🟢 OK — evaluar reducir 5 temp.
A19: Marzo | B19: =IFERROR(IF(SUMIFS(Datos_Volumen!$E:$E,Datos_Volumen!$A:$A,$A$4,Datos_Volumen!$B:$B,$E$4,Datos_Volumen!$C:$C,3)>0,SUMIFS(Datos_Volumen!$E:$E,Datos_Volumen!$A:$A,$A$4,Datos_Volumen!$B:$B,$E$4,Datos_Volumen!$C:$C,3),SUMIFS(Datos_Volumen!$E:$E,Datos_Volumen!$A:$A,$A$4,Datos_Volumen!$B:$B,$E$4-1,Datos_Volumen!$C:$C,3)),0) -> 54213 | C19: =B19*(1+$C$4) -> 59634.3 | D19: =IFERROR(IF(SUMIFS(Datos_Volumen!$F:$F,Datos_Volumen!$A:$A,$A$4,Datos_Volumen!$B:$B,$E$4,Datos_Volumen!$C:$C,3)>0,SUMIFS(Datos_Volumen!$F:$F,Datos_Volumen!$A:$A,$A$4,Datos_Volumen!$B:$B,$E$4,Datos_Volumen!$C:$C,3),SUMIFS(Datos_Volumen!$F:$F,Datos_Volumen!$A:$A,$A$4,Datos_Volumen!$B:$B,$E$4-1,Datos_Volumen!$C:$C,3)),0) -> 5113 | E19: =D19*(1+$C$4) -> 5624.3 | F19: =IFERROR(SUMIFS(Datos_Dotacion!$I:$I,Datos_Dotacion!$A:$A,$A$4,Datos_Dotacion!$B:$B,$E$4,Datos_Dotacion!$C:$C,3),0) -> 10 | G19: =FLOOR(F19*(1-(IFERROR(SUMIFS(Datos_Dotacion!$J:$J,Datos_Dotacion!$A:$A,$A$4,Datos_Dotacion!$B:$B,$E$4,Datos_Dotacion!$C:$C,3),0))),1) -> 9 | H19: =IF($A$4="Casa Central",Tablas_Operativas!B24,Tablas_Operativas!F24) -> 1 | I19: =IFERROR(ROUNDUP((E19/T19/Parametros!$B$7)/Parametros!$B$14,0),0) -> 1 | J19: =IFERROR(ROUNDUP(((IF((IFERROR(SUMIFS(Datos_Vacios!$G:$G,Datos_Vacios!$A:$A,$A$4,Datos_Vacios!$B:$B,$E$4,Datos_Vacios!$C:$C,3,Datos_Vacios!$F:$F,"Sí"),0))>0,(IFERROR(SUMIFS(Datos_Vacios!$G:$G,Datos_Vacios!$A:$A,$A$4,Datos_Vacios!$B:$B,$E$4,Datos_Vacios!$C:$C,3,Datos_Vacios!$F:$F,"Sí"),0)),(IFERROR(SUMIFS(Datos_Vacios!$G:$G,Datos_Vacios!$A:$A,$A$4,Datos_Vacios!$B:$B,$E$4-1,Datos_Vacios!$C:$C,3,Datos_Vacios!$F:$F,"Sí"),0))))*(1+$C$4)/T19/Parametros!$B$8)/Parametros!$B$14,0),0) -> 1 | K19: =MAX(G19-H19-I19-J19,0) -> 6 | L19: =IFERROR(ROUNDUP((C19*(IF($A$4="Casa Central",Tablas_Operativas!B8,Tablas_Operativas!F8))/T19/Parametros!$B$6)/Parametros!$B$16,0),0) -> 2 | M19: =K19-L19 -> 4 | N19: =I19 -> 1 | O19: =IFERROR(SUMIFS(Datos_Dotacion!$K:$K,Datos_Dotacion!$A:$A,$A$4,Datos_Dotacion!$B:$B,$E$4,Datos_Dotacion!$C:$C,3)+SUMIFS(Datos_Dotacion!$L:$L,Datos_Dotacion!$A:$A,$A$4,Datos_Dotacion!$B:$B,$E$4,Datos_Dotacion!$C:$C,3),0) -> 2 | P19: =O19-N19 -> 1 | Q19: =IFERROR(E19/T19/Parametros!$B$7,0) -> 4.9163462 | R19: =IFERROR((IF((IFERROR(SUMIFS(Datos_Vacios!$G:$G,Datos_Vacios!$A:$A,$A$4,Datos_Vacios!$B:$B,$E$4,Datos_Vacios!$C:$C,3,Datos_Vacios!$F:$F,"Sí"),0))>0,(IFERROR(SUMIFS(Datos_Vacios!$G:$G,Datos_Vacios!$A:$A,$A$4,Datos_Vacios!$B:$B,$E$4,Datos_Vacios!$C:$C,3,Datos_Vacios!$F:$F,"Sí"),0)),(IFERROR(SUMIFS(Datos_Vacios!$G:$G,Datos_Vacios!$A:$A,$A$4,Datos_Vacios!$B:$B,$E$4-1,Datos_Vacios!$C:$C,3,Datos_Vacios!$F:$F,"Sí"),0))))*(1+$C$4)/T19/Parametros!$B$8,0) -> 1.9179487 | S19: =IFERROR(C19*(IF($A$4="Casa Central",Tablas_Operativas!B8,Tablas_Operativas!F8))/T19/Parametros!$B$6,0) -> 5.5603077 | T19: =DAY(EOMONTH(DATE($E$4,3,1),0))-SUMPRODUCT((WEEKDAY(DATE($E$4,3,ROW(INDIRECT("1:"&DAY(EOMONTH(DATE($E$4,3,1),0))))),2)=7)*1) -> 26 | U19: =IFERROR((I19*Parametros!$B$14 + J19*Parametros!$B$14 + L19*Parametros!$B$16)/(G19*Parametros!$B$14),0) -> 0.38095238 | V19: =IF(M19<-2,"🔴 CRÍTICO — Contratar "&ABS(M19)&" pickers urgente",IF(M19<0,"🟠 FALTAN "&ABS(M19)&" picker(s) — horas extra o temp.",IF(P19<0,"🟡 FALTAN "&ABS(P19)&" auto(s) — evaluar alquiler",IF(U19>Parametros!$B$13,"🔴 SOBRECARGA "&TEXT(U19,"0%"),IF(U19>Parametros!$B$12,"🟡 RIESGO "&TEXT(U19,"0%"),IF(M19>3,"🟢 OK — evaluar reducir "&(M19-2)&" temp.","🟢 OK")))))) -> 🟢 OK — evaluar reducir 2 temp.
A20: Abril | B20: =IFERROR(IF(SUMIFS(Datos_Volumen!$E:$E,Datos_Volumen!$A:$A,$A$4,Datos_Volumen!$B:$B,$E$4,Datos_Volumen!$C:$C,4)>0,SUMIFS(Datos_Volumen!$E:$E,Datos_Volumen!$A:$A,$A$4,Datos_Volumen!$B:$B,$E$4,Datos_Volumen!$C:$C,4),SUMIFS(Datos_Volumen!$E:$E,Datos_Volumen!$A:$A,$A$4,Datos_Volumen!$B:$B,$E$4-1,Datos_Volumen!$C:$C,4)),0) -> 30159 | C20: =B20*(1+$C$4) -> 33174.9 | D20: =IFERROR(IF(SUMIFS(Datos_Volumen!$F:$F,Datos_Volumen!$A:$A,$A$4,Datos_Volumen!$B:$B,$E$4,Datos_Volumen!$C:$C,4)>0,SUMIFS(Datos_Volumen!$F:$F,Datos_Volumen!$A:$A,$A$4,Datos_Volumen!$B:$B,$E$4,Datos_Volumen!$C:$C,4),SUMIFS(Datos_Volumen!$F:$F,Datos_Volumen!$A:$A,$A$4,Datos_Volumen!$B:$B,$E$4-1,Datos_Volumen!$C:$C,4)),0) -> 2922 | E20: =D20*(1+$C$4) -> 3214.2 | F20: =IFERROR(SUMIFS(Datos_Dotacion!$I:$I,Datos_Dotacion!$A:$A,$A$4,Datos_Dotacion!$B:$B,$E$4,Datos_Dotacion!$C:$C,4),0) -> 6 | G20: =FLOOR(F20*(1-(IFERROR(SUMIFS(Datos_Dotacion!$J:$J,Datos_Dotacion!$A:$A,$A$4,Datos_Dotacion!$B:$B,$E$4,Datos_Dotacion!$C:$C,4),0))),1) -> 5 | H20: =IF($A$4="Casa Central",Tablas_Operativas!B25,Tablas_Operativas!F25) -> 1 | I20: =IFERROR(ROUNDUP((E20/T20/Parametros!$B$7)/Parametros!$B$14,0),0) -> 1 | J20: =IFERROR(ROUNDUP(((IF((IFERROR(SUMIFS(Datos_Vacios!$G:$G,Datos_Vacios!$A:$A,$A$4,Datos_Vacios!$B:$B,$E$4,Datos_Vacios!$C:$C,4,Datos_Vacios!$F:$F,"Sí"),0))>0,(IFERROR(SUMIFS(Datos_Vacios!$G:$G,Datos_Vacios!$A:$A,$A$4,Datos_Vacios!$B:$B,$E$4,Datos_Vacios!$C:$C,4,Datos_Vacios!$F:$F,"Sí"),0)),(IFERROR(SUMIFS(Datos_Vacios!$G:$G,Datos_Vacios!$A:$A,$A$4,Datos_Vacios!$B:$B,$E$4-1,Datos_Vacios!$C:$C,4,Datos_Vacios!$F:$F,"Sí"),0))))*(1+$C$4)/T20/Parametros!$B$8)/Parametros!$B$14,0),0) -> 1 | K20: =MAX(G20-H20-I20-J20,0) -> 2 | L20: =IFERROR(ROUNDUP((C20*(IF($A$4="Casa Central",Tablas_Operativas!B9,Tablas_Operativas!F9))/T20/Parametros!$B$6)/Parametros!$B$16,0),0) -> 1 | M20: =K20-L20 -> 1 | N20: =I20 -> 1 | O20: =IFERROR(SUMIFS(Datos_Dotacion!$K:$K,Datos_Dotacion!$A:$A,$A$4,Datos_Dotacion!$B:$B,$E$4,Datos_Dotacion!$C:$C,4)+SUMIFS(Datos_Dotacion!$L:$L,Datos_Dotacion!$A:$A,$A$4,Datos_Dotacion!$B:$B,$E$4,Datos_Dotacion!$C:$C,4),0) -> 2 | P20: =O20-N20 -> 1 | Q20: =IFERROR(E20/T20/Parametros!$B$7,0) -> 2.8096154 | R20: =IFERROR((IF((IFERROR(SUMIFS(Datos_Vacios!$G:$G,Datos_Vacios!$A:$A,$A$4,Datos_Vacios!$B:$B,$E$4,Datos_Vacios!$C:$C,4,Datos_Vacios!$F:$F,"Sí"),0))>0,(IFERROR(SUMIFS(Datos_Vacios!$G:$G,Datos_Vacios!$A:$A,$A$4,Datos_Vacios!$B:$B,$E$4,Datos_Vacios!$C:$C,4,Datos_Vacios!$F:$F,"Sí"),0)),(IFERROR(SUMIFS(Datos_Vacios!$G:$G,Datos_Vacios!$A:$A,$A$4,Datos_Vacios!$B:$B,$E$4-1,Datos_Vacios!$C:$C,4,Datos_Vacios!$F:$F,"Sí"),0))))*(1+$C$4)/T20/Parametros!$B$8,0) -> 1.2504274 | S20: =IFERROR(C20*(IF($A$4="Casa Central",Tablas_Operativas!B9,Tablas_Operativas!F9))/T20/Parametros!$B$6,0) -> 3.0932308 | T20: =DAY(EOMONTH(DATE($E$4,4,1),0))-SUMPRODUCT((WEEKDAY(DATE($E$4,4,ROW(INDIRECT("1:"&DAY(EOMONTH(DATE($E$4,4,1),0))))),2)=7)*1) -> 26 | U20: =IFERROR((I20*Parametros!$B$14 + J20*Parametros!$B$14 + L20*Parametros!$B$16)/(G20*Parametros!$B$14),0) -> 0.54285714 | V20: =IF(M20<-2,"🔴 CRÍTICO — Contratar "&ABS(M20)&" pickers urgente",IF(M20<0,"🟠 FALTAN "&ABS(M20)&" picker(s) — horas extra o temp.",IF(P20<0,"🟡 FALTAN "&ABS(P20)&" auto(s) — evaluar alquiler",IF(U20>Parametros!$B$13,"🔴 SOBRECARGA "&TEXT(U20,"0%"),IF(U20>Parametros!$B$12,"🟡 RIESGO "&TEXT(U20,"0%"),IF(M20>3,"🟢 OK — evaluar reducir "&(M20-2)&" temp.","🟢 OK")))))) -> 🟢 OK
A21: Mayo | B21: =IFERROR(IF(SUMIFS(Datos_Volumen!$E:$E,Datos_Volumen!$A:$A,$A$4,Datos_Volumen!$B:$B,$E$4,Datos_Volumen!$C:$C,5)>0,SUMIFS(Datos_Volumen!$E:$E,Datos_Volumen!$A:$A,$A$4,Datos_Volumen!$B:$B,$E$4,Datos_Volumen!$C:$C,5),SUMIFS(Datos_Volumen!$E:$E,Datos_Volumen!$A:$A,$A$4,Datos_Volumen!$B:$B,$E$4-1,Datos_Volumen!$C:$C,5)),0) -> 23491 | C21: =B21*(1+$C$4) -> 25840.1 | D21: =IFERROR(IF(SUMIFS(Datos_Volumen!$F:$F,Datos_Volumen!$A:$A,$A$4,Datos_Volumen!$B:$B,$E$4,Datos_Volumen!$C:$C,5)>0,SUMIFS(Datos_Volumen!$F:$F,Datos_Volumen!$A:$A,$A$4,Datos_Volumen!$B:$B,$E$4,Datos_Volumen!$C:$C,5),SUMIFS(Datos_Volumen!$F:$F,Datos_Volumen!$A:$A,$A$4,Datos_Volumen!$B:$B,$E$4-1,Datos_Volumen!$C:$C,5)),0) -> 2359 | E21: =D21*(1+$C$4) -> 2594.9 | F21: =IFERROR(SUMIFS(Datos_Dotacion!$I:$I,Datos_Dotacion!$A:$A,$A$4,Datos_Dotacion!$B:$B,$E$4,Datos_Dotacion!$C:$C,5),0) -> 6 | G21: =FLOOR(F21*(1-(IFERROR(SUMIFS(Datos_Dotacion!$J:$J,Datos_Dotacion!$A:$A,$A$4,Datos_Dotacion!$B:$B,$E$4,Datos_Dotacion!$C:$C,5),0))),1) -> 5 | H21: =IF($A$4="Casa Central",Tablas_Operativas!B26,Tablas_Operativas!F26) -> 1 | I21: =IFERROR(ROUNDUP((E21/T21/Parametros!$B$7)/Parametros!$B$14,0),0) -> 1 | J21: =IFERROR(ROUNDUP(((IF((IFERROR(SUMIFS(Datos_Vacios!$G:$G,Datos_Vacios!$A:$A,$A$4,Datos_Vacios!$B:$B,$E$4,Datos_Vacios!$C:$C,5,Datos_Vacios!$F:$F,"Sí"),0))>0,(IFERROR(SUMIFS(Datos_Vacios!$G:$G,Datos_Vacios!$A:$A,$A$4,Datos_Vacios!$B:$B,$E$4,Datos_Vacios!$C:$C,5,Datos_Vacios!$F:$F,"Sí"),0)),(IFERROR(SUMIFS(Datos_Vacios!$G:$G,Datos_Vacios!$A:$A,$A$4,Datos_Vacios!$B:$B,$E$4-1,Datos_Vacios!$C:$C,5,Datos_Vacios!$F:$F,"Sí"),0))))*(1+$C$4)/T21/Parametros!$B$8)/Parametros!$B$14,0),0) -> 1 | K21: =MAX(G21-H21-I21-J21,0) -> 2 | L21: =IFERROR(ROUNDUP((C21*(IF($A$4="Casa Central",Tablas_Operativas!B10,Tablas_Operativas!F10))/T21/Parametros!$B$6)/Parametros!$B$16,0),0) -> 1 | M21: =K21-L21 -> 1 | N21: =I21 -> 1 | O21: =IFERROR(SUMIFS(Datos_Dotacion!$K:$K,Datos_Dotacion!$A:$A,$A$4,Datos_Dotacion!$B:$B,$E$4,Datos_Dotacion!$C:$C,5)+SUMIFS(Datos_Dotacion!$L:$L,Datos_Dotacion!$A:$A,$A$4,Datos_Dotacion!$B:$B,$E$4,Datos_Dotacion!$C:$C,5),0) -> 2 | P21: =O21-N21 -> 1 | Q21: =IFERROR(E21/T21/Parametros!$B$7,0) -> 2.2682692 | R21: =IFERROR((IF((IFERROR(SUMIFS(Datos_Vacios!$G:$G,Datos_Vacios!$A:$A,$A$4,Datos_Vacios!$B:$B,$E$4,Datos_Vacios!$C:$C,5,Datos_Vacios!$F:$F,"Sí"),0))>0,(IFERROR(SUMIFS(Datos_Vacios!$G:$G,Datos_Vacios!$A:$A,$A$4,Datos_Vacios!$B:$B,$E$4,Datos_Vacios!$C:$C,5,Datos_Vacios!$F:$F,"Sí"),0)),(IFERROR(SUMIFS(Datos_Vacios!$G:$G,Datos_Vacios!$A:$A,$A$4,Datos_Vacios!$B:$B,$E$4-1,Datos_Vacios!$C:$C,5,Datos_Vacios!$F:$F,"Sí"),0))))*(1+$C$4)/T21/Parametros!$B$8,0) -> 0.94017094 | S21: =IFERROR(C21*(IF($A$4="Casa Central",Tablas_Operativas!B10,Tablas_Operativas!F10))/T21/Parametros!$B$6,0) -> 2.4093333 | T21: =DAY(EOMONTH(DATE($E$4,5,1),0))-SUMPRODUCT((WEEKDAY(DATE($E$4,5,ROW(INDIRECT("1:"&DAY(EOMONTH(DATE($E$4,5,1),0))))),2)=7)*1) -> 26 | U21: =IFERROR((I21*Parametros!$B$14 + J21*Parametros!$B$14 + L21*Parametros!$B$16)/(G21*Parametros!$B$14),0) -> 0.54285714 | V21: =IF(M21<-2,"🔴 CRÍTICO — Contratar "&ABS(M21)&" pickers urgente",IF(M21<0,"🟠 FALTAN "&ABS(M21)&" picker(s) — horas extra o temp.",IF(P21<0,"🟡 FALTAN "&ABS(P21)&" auto(s) — evaluar alquiler",IF(U21>Parametros!$B$13,"🔴 SOBRECARGA "&TEXT(U21,"0%"),IF(U21>Parametros!$B$12,"🟡 RIESGO "&TEXT(U21,"0%"),IF(M21>3,"🟢 OK — evaluar reducir "&(M21-2)&" temp.","🟢 OK")))))) -> 🟢 OK
A22: Junio | B22: =IFERROR(IF(SUMIFS(Datos_Volumen!$E:$E,Datos_Volumen!$A:$A,$A$4,Datos_Volumen!$B:$B,$E$4,Datos_Volumen!$C:$C,6)>0,SUMIFS(Datos_Volumen!$E:$E,Datos_Volumen!$A:$A,$A$4,Datos_Volumen!$B:$B,$E$4,Datos_Volumen!$C:$C,6),SUMIFS(Datos_Volumen!$E:$E,Datos_Volumen!$A:$A,$A$4,Datos_Volumen!$B:$B,$E$4-1,Datos_Volumen!$C:$C,6)),0) -> 30400 | C22: =B22*(1+$C$4) -> 33440 | D22: =IFERROR(IF(SUMIFS(Datos_Volumen!$F:$F,Datos_Volumen!$A:$A,$A$4,Datos_Volumen!$B:$B,$E$4,Datos_Volumen!$C:$C,6)>0,SUMIFS(Datos_Volumen!$F:$F,Datos_Volumen!$A:$A,$A$4,Datos_Volumen!$B:$B,$E$4,Datos_Volumen!$C:$C,6),SUMIFS(Datos_Volumen!$F:$F,Datos_Volumen!$A:$A,$A$4,Datos_Volumen!$B:$B,$E$4-1,Datos_Volumen!$C:$C,6)),0) -> 2984 | E22: =D22*(1+$C$4) -> 3282.4 | F22: =IFERROR(SUMIFS(Datos_Dotacion!$I:$I,Datos_Dotacion!$A:$A,$A$4,Datos_Dotacion!$B:$B,$E$4,Datos_Dotacion!$C:$C,6),0) -> 6 | G22: =FLOOR(F22*(1-(IFERROR(SUMIFS(Datos_Dotacion!$J:$J,Datos_Dotacion!$A:$A,$A$4,Datos_Dotacion!$B:$B,$E$4,Datos_Dotacion!$C:$C,6),0))),1) -> 5 | H22: =IF($A$4="Casa Central",Tablas_Operativas!B27,Tablas_Operativas!F27) -> 1 | I22: =IFERROR(ROUNDUP((E22/T22/Parametros!$B$7)/Parametros!$B$14,0),0) -> 1 | J22: =IFERROR(ROUNDUP(((IF((IFERROR(SUMIFS(Datos_Vacios!$G:$G,Datos_Vacios!$A:$A,$A$4,Datos_Vacios!$B:$B,$E$4,Datos_Vacios!$C:$C,6,Datos_Vacios!$F:$F,"Sí"),0))>0,(IFERROR(SUMIFS(Datos_Vacios!$G:$G,Datos_Vacios!$A:$A,$A$4,Datos_Vacios!$B:$B,$E$4,Datos_Vacios!$C:$C,6,Datos_Vacios!$F:$F,"Sí"),0)),(IFERROR(SUMIFS(Datos_Vacios!$G:$G,Datos_Vacios!$A:$A,$A$4,Datos_Vacios!$B:$B,$E$4-1,Datos_Vacios!$C:$C,6,Datos_Vacios!$F:$F,"Sí"),0))))*(1+$C$4)/T22/Parametros!$B$8)/Parametros!$B$14,0),0) -> 1 | K22: =MAX(G22-H22-I22-J22,0) -> 2 | L22: =IFERROR(ROUNDUP((C22*(IF($A$4="Casa Central",Tablas_Operativas!B11,Tablas_Operativas!F11))/T22/Parametros!$B$6)/Parametros!$B$16,0),0) -> 1 | M22: =K22-L22 -> 1 | N22: =I22 -> 1 | O22: =IFERROR(SUMIFS(Datos_Dotacion!$K:$K,Datos_Dotacion!$A:$A,$A$4,Datos_Dotacion!$B:$B,$E$4,Datos_Dotacion!$C:$C,6)+SUMIFS(Datos_Dotacion!$L:$L,Datos_Dotacion!$A:$A,$A$4,Datos_Dotacion!$B:$B,$E$4,Datos_Dotacion!$C:$C,6),0) -> 2 | P22: =O22-N22 -> 1 | Q22: =IFERROR(E22/T22/Parametros!$B$7,0) -> 2.8692308 | R22: =IFERROR((IF((IFERROR(SUMIFS(Datos_Vacios!$G:$G,Datos_Vacios!$A:$A,$A$4,Datos_Vacios!$B:$B,$E$4,Datos_Vacios!$C:$C,6,Datos_Vacios!$F:$F,"Sí"),0))>0,(IFERROR(SUMIFS(Datos_Vacios!$G:$G,Datos_Vacios!$A:$A,$A$4,Datos_Vacios!$B:$B,$E$4,Datos_Vacios!$C:$C,6,Datos_Vacios!$F:$F,"Sí"),0)),(IFERROR(SUMIFS(Datos_Vacios!$G:$G,Datos_Vacios!$A:$A,$A$4,Datos_Vacios!$B:$B,$E$4-1,Datos_Vacios!$C:$C,6,Datos_Vacios!$F:$F,"Sí"),0))))*(1+$C$4)/T22/Parametros!$B$8,0) -> 0.9025641 | S22: =IFERROR(C22*(IF($A$4="Casa Central",Tablas_Operativas!B11,Tablas_Operativas!F11))/T22/Parametros!$B$6,0) -> 3.1179487 | T22: =DAY(EOMONTH(DATE($E$4,6,1),0))-SUMPRODUCT((WEEKDAY(DATE($E$4,6,ROW(INDIRECT("1:"&DAY(EOMONTH(DATE($E$4,6,1),0))))),2)=7)*1) -> 26 | U22: =IFERROR((I22*Parametros!$B$14 + J22*Parametros!$B$14 + L22*Parametros!$B$16)/(G22*Parametros!$B$14),0) -> 0.54285714 | V22: =IF(M22<-2,"🔴 CRÍTICO — Contratar "&ABS(M22)&" pickers urgente",IF(M22<0,"🟠 FALTAN "&ABS(M22)&" picker(s) — horas extra o temp.",IF(P22<0,"🟡 FALTAN "&ABS(P22)&" auto(s) — evaluar alquiler",IF(U22>Parametros!$B$13,"🔴 SOBRECARGA "&TEXT(U22,"0%"),IF(U22>Parametros!$B$12,"🟡 RIESGO "&TEXT(U22,"0%"),IF(M22>3,"🟢 OK — evaluar reducir "&(M22-2)&" temp.","🟢 OK")))))) -> 🟢 OK
A23: Julio | B23: =IFERROR(IF(SUMIFS(Datos_Volumen!$E:$E,Datos_Volumen!$A:$A,$A$4,Datos_Volumen!$B:$B,$E$4,Datos_Volumen!$C:$C,7)>0,SUMIFS(Datos_Volumen!$E:$E,Datos_Volumen!$A:$A,$A$4,Datos_Volumen!$B:$B,$E$4,Datos_Volumen!$C:$C,7),SUMIFS(Datos_Volumen!$E:$E,Datos_Volumen!$A:$A,$A$4,Datos_Volumen!$B:$B,$E$4-1,Datos_Volumen!$C:$C,7)),0) -> 39209 | C23: =B23*(1+$C$4) -> 43129.9 | D23: =IFERROR(IF(SUMIFS(Datos_Volumen!$F:$F,Datos_Volumen!$A:$A,$A$4,Datos_Volumen!$B:$B,$E$4,Datos_Volumen!$C:$C,7)>0,SUMIFS(Datos_Volumen!$F:$F,Datos_Volumen!$A:$A,$A$4,Datos_Volumen!$B:$B,$E$4,Datos_Volumen!$C:$C,7),SUMIFS(Datos_Volumen!$F:$F,Datos_Volumen!$A:$A,$A$4,Datos_Volumen!$B:$B,$E$4-1,Datos_Volumen!$C:$C,7)),0) -> 3858 | E23: =D23*(1+$C$4) -> 4243.8 | F23: =IFERROR(SUMIFS(Datos_Dotacion!$I:$I,Datos_Dotacion!$A:$A,$A$4,Datos_Dotacion!$B:$B,$E$4,Datos_Dotacion!$C:$C,7),0) -> 6 | G23: =FLOOR(F23*(1-(IFERROR(SUMIFS(Datos_Dotacion!$J:$J,Datos_Dotacion!$A:$A,$A$4,Datos_Dotacion!$B:$B,$E$4,Datos_Dotacion!$C:$C,7),0))),1) -> 5 | H23: =IF($A$4="Casa Central",Tablas_Operativas!B28,Tablas_Operativas!F28) -> 1 | I23: =IFERROR(ROUNDUP((E23/T23/Parametros!$B$7)/Parametros!$B$14,0),0) -> 1 | J23: =IFERROR(ROUNDUP(((IF((IFERROR(SUMIFS(Datos_Vacios!$G:$G,Datos_Vacios!$A:$A,$A$4,Datos_Vacios!$B:$B,$E$4,Datos_Vacios!$C:$C,7,Datos_Vacios!$F:$F,"Sí"),0))>0,(IFERROR(SUMIFS(Datos_Vacios!$G:$G,Datos_Vacios!$A:$A,$A$4,Datos_Vacios!$B:$B,$E$4,Datos_Vacios!$C:$C,7,Datos_Vacios!$F:$F,"Sí"),0)),(IFERROR(SUMIFS(Datos_Vacios!$G:$G,Datos_Vacios!$A:$A,$A$4,Datos_Vacios!$B:$B,$E$4-1,Datos_Vacios!$C:$C,7,Datos_Vacios!$F:$F,"Sí"),0))))*(1+$C$4)/T23/Parametros!$B$8)/Parametros!$B$14,0),0) -> 1 | K23: =MAX(G23-H23-I23-J23,0) -> 2 | L23: =IFERROR(ROUNDUP((C23*(IF($A$4="Casa Central",Tablas_Operativas!B12,Tablas_Operativas!F12))/T23/Parametros!$B$6)/Parametros!$B$16,0),0) -> 1 | M23: =K23-L23 -> 1 | N23: =I23 -> 1 | O23: =IFERROR(SUMIFS(Datos_Dotacion!$K:$K,Datos_Dotacion!$A:$A,$A$4,Datos_Dotacion!$B:$B,$E$4,Datos_Dotacion!$C:$C,7)+SUMIFS(Datos_Dotacion!$L:$L,Datos_Dotacion!$A:$A,$A$4,Datos_Dotacion!$B:$B,$E$4,Datos_Dotacion!$C:$C,7),0) -> 2 | P23: =O23-N23 -> 1 | Q23: =IFERROR(E23/T23/Parametros!$B$7,0) -> 3.5722222 | R23: =IFERROR((IF((IFERROR(SUMIFS(Datos_Vacios!$G:$G,Datos_Vacios!$A:$A,$A$4,Datos_Vacios!$B:$B,$E$4,Datos_Vacios!$C:$C,7,Datos_Vacios!$F:$F,"Sí"),0))>0,(IFERROR(SUMIFS(Datos_Vacios!$G:$G,Datos_Vacios!$A:$A,$A$4,Datos_Vacios!$B:$B,$E$4,Datos_Vacios!$C:$C,7,Datos_Vacios!$F:$F,"Sí"),0)),(IFERROR(SUMIFS(Datos_Vacios!$G:$G,Datos_Vacios!$A:$A,$A$4,Datos_Vacios!$B:$B,$E$4-1,Datos_Vacios!$C:$C,7,Datos_Vacios!$F:$F,"Sí"),0))))*(1+$C$4)/T23/Parametros!$B$8,0) -> 1.0320988 | S23: =IFERROR(C23*(IF($A$4="Casa Central",Tablas_Operativas!B12,Tablas_Operativas!F12))/T23/Parametros!$B$6,0) -> 3.8724938 | T23: =DAY(EOMONTH(DATE($E$4,7,1),0))-SUMPRODUCT((WEEKDAY(DATE($E$4,7,ROW(INDIRECT("1:"&DAY(EOMONTH(DATE($E$4,7,1),0))))),2)=7)*1) -> 27 | U23: =IFERROR((I23*Parametros!$B$14 + J23*Parametros!$B$14 + L23*Parametros!$B$16)/(G23*Parametros!$B$14),0) -> 0.54285714 | V23: =IF(M23<-2,"🔴 CRÍTICO — Contratar "&ABS(M23)&" pickers urgente",IF(M23<0,"🟠 FALTAN "&ABS(M23)&" picker(s) — horas extra o temp.",IF(P23<0,"🟡 FALTAN "&ABS(P23)&" auto(s) — evaluar alquiler",IF(U23>Parametros!$B$13,"🔴 SOBRECARGA "&TEXT(U23,"0%"),IF(U23>Parametros!$B$12,"🟡 RIESGO "&TEXT(U23,"0%"),IF(M23>3,"🟢 OK — evaluar reducir "&(M23-2)&" temp.","🟢 OK")))))) -> 🟢 OK
A24: Agosto | B24: =IFERROR(IF(SUMIFS(Datos_Volumen!$E:$E,Datos_Volumen!$A:$A,$A$4,Datos_Volumen!$B:$B,$E$4,Datos_Volumen!$C:$C,8)>0,SUMIFS(Datos_Volumen!$E:$E,Datos_Volumen!$A:$A,$A$4,Datos_Volumen!$B:$B,$E$4,Datos_Volumen!$C:$C,8),SUMIFS(Datos_Volumen!$E:$E,Datos_Volumen!$A:$A,$A$4,Datos_Volumen!$B:$B,$E$4-1,Datos_Volumen!$C:$C,8)),0) -> 40289 | C24: =B24*(1+$C$4) -> 44317.9 | D24: =IFERROR(IF(SUMIFS(Datos_Volumen!$F:$F,Datos_Volumen!$A:$A,$A$4,Datos_Volumen!$B:$B,$E$4,Datos_Volumen!$C:$C,8)>0,SUMIFS(Datos_Volumen!$F:$F,Datos_Volumen!$A:$A,$A$4,Datos_Volumen!$B:$B,$E$4,Datos_Volumen!$C:$C,8),SUMIFS(Datos_Volumen!$F:$F,Datos_Volumen!$A:$A,$A$4,Datos_Volumen!$B:$B,$E$4-1,Datos_Volumen!$C:$C,8)),0) -> 4028 | E24: =D24*(1+$C$4) -> 4430.8 | F24: =IFERROR(SUMIFS(Datos_Dotacion!$I:$I,Datos_Dotacion!$A:$A,$A$4,Datos_Dotacion!$B:$B,$E$4,Datos_Dotacion!$C:$C,8),0) -> 6 | G24: =FLOOR(F24*(1-(IFERROR(SUMIFS(Datos_Dotacion!$J:$J,Datos_Dotacion!$A:$A,$A$4,Datos_Dotacion!$B:$B,$E$4,Datos_Dotacion!$C:$C,8),0))),1) -> 5 | H24: =IF($A$4="Casa Central",Tablas_Operativas!B29,Tablas_Operativas!F29) -> 1 | I24: =IFERROR(ROUNDUP((E24/T24/Parametros!$B$7)/Parametros!$B$14,0),0) -> 1 | J24: =IFERROR(ROUNDUP(((IF((IFERROR(SUMIFS(Datos_Vacios!$G:$G,Datos_Vacios!$A:$A,$A$4,Datos_Vacios!$B:$B,$E$4,Datos_Vacios!$C:$C,8,Datos_Vacios!$F:$F,"Sí"),0))>0,(IFERROR(SUMIFS(Datos_Vacios!$G:$G,Datos_Vacios!$A:$A,$A$4,Datos_Vacios!$B:$B,$E$4,Datos_Vacios!$C:$C,8,Datos_Vacios!$F:$F,"Sí"),0)),(IFERROR(SUMIFS(Datos_Vacios!$G:$G,Datos_Vacios!$A:$A,$A$4,Datos_Vacios!$B:$B,$E$4-1,Datos_Vacios!$C:$C,8,Datos_Vacios!$F:$F,"Sí"),0))))*(1+$C$4)/T24/Parametros!$B$8)/Parametros!$B$14,0),0) -> 1 | K24: =MAX(G24-H24-I24-J24,0) -> 2 | L24: =IFERROR(ROUNDUP((C24*(IF($A$4="Casa Central",Tablas_Operativas!B13,Tablas_Operativas!F13))/T24/Parametros!$B$6)/Parametros!$B$16,0),0) -> 1 | M24: =K24-L24 -> 1 | N24: =I24 -> 1 | O24: =IFERROR(SUMIFS(Datos_Dotacion!$K:$K,Datos_Dotacion!$A:$A,$A$4,Datos_Dotacion!$B:$B,$E$4,Datos_Dotacion!$C:$C,8)+SUMIFS(Datos_Dotacion!$L:$L,Datos_Dotacion!$A:$A,$A$4,Datos_Dotacion!$B:$B,$E$4,Datos_Dotacion!$C:$C,8),0) -> 2 | P24: =O24-N24 -> 1 | Q24: =IFERROR(E24/T24/Parametros!$B$7,0) -> 3.8730769 | R24: =IFERROR((IF((IFERROR(SUMIFS(Datos_Vacios!$G:$G,Datos_Vacios!$A:$A,$A$4,Datos_Vacios!$B:$B,$E$4,Datos_Vacios!$C:$C,8,Datos_Vacios!$F:$F,"Sí"),0))>0,(IFERROR(SUMIFS(Datos_Vacios!$G:$G,Datos_Vacios!$A:$A,$A$4,Datos_Vacios!$B:$B,$E$4,Datos_Vacios!$C:$C,8,Datos_Vacios!$F:$F,"Sí"),0)),(IFERROR(SUMIFS(Datos_Vacios!$G:$G,Datos_Vacios!$A:$A,$A$4,Datos_Vacios!$B:$B,$E$4-1,Datos_Vacios!$C:$C,8,Datos_Vacios!$F:$F,"Sí"),0))))*(1+$C$4)/T24/Parametros!$B$8,0) -> 1.3820513 | S24: =IFERROR(C24*(IF($A$4="Casa Central",Tablas_Operativas!B13,Tablas_Operativas!F13))/T24/Parametros!$B$6,0) -> 4.1322051 | T24: =DAY(EOMONTH(DATE($E$4,8,1),0))-SUMPRODUCT((WEEKDAY(DATE($E$4,8,ROW(INDIRECT("1:"&DAY(EOMONTH(DATE($E$4,8,1),0))))),2)=7)*1) -> 26 | U24: =IFERROR((I24*Parametros!$B$14 + J24*Parametros!$B$14 + L24*Parametros!$B$16)/(G24*Parametros!$B$14),0) -> 0.54285714 | V24: =IF(M24<-2,"🔴 CRÍTICO — Contratar "&ABS(M24)&" pickers urgente",IF(M24<0,"🟠 FALTAN "&ABS(M24)&" picker(s) — horas extra o temp.",IF(P24<0,"🟡 FALTAN "&ABS(P24)&" auto(s) — evaluar alquiler",IF(U24>Parametros!$B$13,"🔴 SOBRECARGA "&TEXT(U24,"0%"),IF(U24>Parametros!$B$12,"🟡 RIESGO "&TEXT(U24,"0%"),IF(M24>3,"🟢 OK — evaluar reducir "&(M24-2)&" temp.","🟢 OK")))))) -> 🟢 OK
A25: Septiembre | B25: =IFERROR(IF(SUMIFS(Datos_Volumen!$E:$E,Datos_Volumen!$A:$A,$A$4,Datos_Volumen!$B:$B,$E$4,Datos_Volumen!$C:$C,9)>0,SUMIFS(Datos_Volumen!$E:$E,Datos_Volumen!$A:$A,$A$4,Datos_Volumen!$B:$B,$E$4,Datos_Volumen!$C:$C,9),SUMIFS(Datos_Volumen!$E:$E,Datos_Volumen!$A:$A,$A$4,Datos_Volumen!$B:$B,$E$4-1,Datos_Volumen!$C:$C,9)),0) -> 23148 | C25: =B25*(1+$C$4) -> 25462.8 | D25: =IFERROR(IF(SUMIFS(Datos_Volumen!$F:$F,Datos_Volumen!$A:$A,$A$4,Datos_Volumen!$B:$B,$E$4,Datos_Volumen!$C:$C,9)>0,SUMIFS(Datos_Volumen!$F:$F,Datos_Volumen!$A:$A,$A$4,Datos_Volumen!$B:$B,$E$4,Datos_Volumen!$C:$C,9),SUMIFS(Datos_Volumen!$F:$F,Datos_Volumen!$A:$A,$A$4,Datos_Volumen!$B:$B,$E$4-1,Datos_Volumen!$C:$C,9)),0) -> 2117 | E25: =D25*(1+$C$4) -> 2328.7 | F25: =IFERROR(SUMIFS(Datos_Dotacion!$I:$I,Datos_Dotacion!$A:$A,$A$4,Datos_Dotacion!$B:$B,$E$4,Datos_Dotacion!$C:$C,9),0) -> 6 | G25: =FLOOR(F25*(1-(IFERROR(SUMIFS(Datos_Dotacion!$J:$J,Datos_Dotacion!$A:$A,$A$4,Datos_Dotacion!$B:$B,$E$4,Datos_Dotacion!$C:$C,9),0))),1) -> 5 | H25: =IF($A$4="Casa Central",Tablas_Operativas!B30,Tablas_Operativas!F30) -> 1 | I25: =IFERROR(ROUNDUP((E25/T25/Parametros!$B$7)/Parametros!$B$14,0),0) -> 1 | J25: =IFERROR(ROUNDUP(((IF((IFERROR(SUMIFS(Datos_Vacios!$G:$G,Datos_Vacios!$A:$A,$A$4,Datos_Vacios!$B:$B,$E$4,Datos_Vacios!$C:$C,9,Datos_Vacios!$F:$F,"Sí"),0))>0,(IFERROR(SUMIFS(Datos_Vacios!$G:$G,Datos_Vacios!$A:$A,$A$4,Datos_Vacios!$B:$B,$E$4,Datos_Vacios!$C:$C,9,Datos_Vacios!$F:$F,"Sí"),0)),(IFERROR(SUMIFS(Datos_Vacios!$G:$G,Datos_Vacios!$A:$A,$A$4,Datos_Vacios!$B:$B,$E$4-1,Datos_Vacios!$C:$C,9,Datos_Vacios!$F:$F,"Sí"),0))))*(1+$C$4)/T25/Parametros!$B$8)/Parametros!$B$14,0),0) -> 1 | K25: =MAX(G25-H25-I25-J25,0) -> 2 | L25: =IFERROR(ROUNDUP((C25*(IF($A$4="Casa Central",Tablas_Operativas!B14,Tablas_Operativas!F14))/T25/Parametros!$B$6)/Parametros!$B$16,0),0) -> 1 | M25: =K25-L25 -> 1 | N25: =I25 -> 1 | O25: =IFERROR(SUMIFS(Datos_Dotacion!$K:$K,Datos_Dotacion!$A:$A,$A$4,Datos_Dotacion!$B:$B,$E$4,Datos_Dotacion!$C:$C,9)+SUMIFS(Datos_Dotacion!$L:$L,Datos_Dotacion!$A:$A,$A$4,Datos_Dotacion!$B:$B,$E$4,Datos_Dotacion!$C:$C,9),0) -> 2 | P25: =O25-N25 -> 1 | Q25: =IFERROR(E25/T25/Parametros!$B$7,0) -> 2.0355769 | R25: =IFERROR((IF((IFERROR(SUMIFS(Datos_Vacios!$G:$G,Datos_Vacios!$A:$A,$A$4,Datos_Vacios!$B:$B,$E$4,Datos_Vacios!$C:$C,9,Datos_Vacios!$F:$F,"Sí"),0))>0,(IFERROR(SUMIFS(Datos_Vacios!$G:$G,Datos_Vacios!$A:$A,$A$4,Datos_Vacios!$B:$B,$E$4,Datos_Vacios!$C:$C,9,Datos_Vacios!$F:$F,"Sí"),0)),(IFERROR(SUMIFS(Datos_Vacios!$G:$G,Datos_Vacios!$A:$A,$A$4,Datos_Vacios!$B:$B,$E$4-1,Datos_Vacios!$C:$C,9,Datos_Vacios!$F:$F,"Sí"),0))))*(1+$C$4)/T25/Parametros!$B$8,0) -> 0.64871795 | S25: =IFERROR(C25*(IF($A$4="Casa Central",Tablas_Operativas!B14,Tablas_Operativas!F14))/T25/Parametros!$B$6,0) -> 2.3741538 | T25: =DAY(EOMONTH(DATE($E$4,9,1),0))-SUMPRODUCT((WEEKDAY(DATE($E$4,9,ROW(INDIRECT("1:"&DAY(EOMONTH(DATE($E$4,9,1),0))))),2)=7)*1) -> 26 | U25: =IFERROR((I25*Parametros!$B$14 + J25*Parametros!$B$14 + L25*Parametros!$B$16)/(G25*Parametros!$B$14),0) -> 0.54285714 | V25: =IF(M25<-2,"🔴 CRÍTICO — Contratar "&ABS(M25)&" pickers urgente",IF(M25<0,"🟠 FALTAN "&ABS(M25)&" picker(s) — horas extra o temp.",IF(P25<0,"🟡 FALTAN "&ABS(P25)&" auto(s) — evaluar alquiler",IF(U25>Parametros!$B$13,"🔴 SOBRECARGA "&TEXT(U25,"0%"),IF(U25>Parametros!$B$12,"🟡 RIESGO "&TEXT(U25,"0%"),IF(M25>3,"🟢 OK — evaluar reducir "&(M25-2)&" temp.","🟢 OK")))))) -> 🟢 OK
A26: Octubre | B26: =IFERROR(IF(SUMIFS(Datos_Volumen!$E:$E,Datos_Volumen!$A:$A,$A$4,Datos_Volumen!$B:$B,$E$4,Datos_Volumen!$C:$C,10)>0,SUMIFS(Datos_Volumen!$E:$E,Datos_Volumen!$A:$A,$A$4,Datos_Volumen!$B:$B,$E$4,Datos_Volumen!$C:$C,10),SUMIFS(Datos_Volumen!$E:$E,Datos_Volumen!$A:$A,$A$4,Datos_Volumen!$B:$B,$E$4-1,Datos_Volumen!$C:$C,10)),0) -> 47723 | C26: =B26*(1+$C$4) -> 52495.3 | D26: =IFERROR(IF(SUMIFS(Datos_Volumen!$F:$F,Datos_Volumen!$A:$A,$A$4,Datos_Volumen!$B:$B,$E$4,Datos_Volumen!$C:$C,10)>0,SUMIFS(Datos_Volumen!$F:$F,Datos_Volumen!$A:$A,$A$4,Datos_Volumen!$B:$B,$E$4,Datos_Volumen!$C:$C,10),SUMIFS(Datos_Volumen!$F:$F,Datos_Volumen!$A:$A,$A$4,Datos_Volumen!$B:$B,$E$4-1,Datos_Volumen!$C:$C,10)),0) -> 4748 | E26: =D26*(1+$C$4) -> 5222.8 | F26: =IFERROR(SUMIFS(Datos_Dotacion!$I:$I,Datos_Dotacion!$A:$A,$A$4,Datos_Dotacion!$B:$B,$E$4,Datos_Dotacion!$C:$C,10),0) -> 7 | G26: =FLOOR(F26*(1-(IFERROR(SUMIFS(Datos_Dotacion!$J:$J,Datos_Dotacion!$A:$A,$A$4,Datos_Dotacion!$B:$B,$E$4,Datos_Dotacion!$C:$C,10),0))),1) -> 6 | H26: =IF($A$4="Casa Central",Tablas_Operativas!B31,Tablas_Operativas!F31) -> 2 | I26: =IFERROR(ROUNDUP((E26/T26/Parametros!$B$7)/Parametros!$B$14,0),0) -> 1 | J26: =IFERROR(ROUNDUP(((IF((IFERROR(SUMIFS(Datos_Vacios!$G:$G,Datos_Vacios!$A:$A,$A$4,Datos_Vacios!$B:$B,$E$4,Datos_Vacios!$C:$C,10,Datos_Vacios!$F:$F,"Sí"),0))>0,(IFERROR(SUMIFS(Datos_Vacios!$G:$G,Datos_Vacios!$A:$A,$A$4,Datos_Vacios!$B:$B,$E$4,Datos_Vacios!$C:$C,10,Datos_Vacios!$F:$F,"Sí"),0)),(IFERROR(SUMIFS(Datos_Vacios!$G:$G,Datos_Vacios!$A:$A,$A$4,Datos_Vacios!$B:$B,$E$4-1,Datos_Vacios!$C:$C,10,Datos_Vacios!$F:$F,"Sí"),0))))*(1+$C$4)/T26/Parametros!$B$8)/Parametros!$B$14,0),0) -> 1 | K26: =MAX(G26-H26-I26-J26,0) -> 2 | L26: =IFERROR(ROUNDUP((C26*(IF($A$4="Casa Central",Tablas_Operativas!B15,Tablas_Operativas!F15))/T26/Parametros!$B$6)/Parametros!$B$16,0),0) -> 1 | M26: =K26-L26 -> 1 | N26: =I26 -> 1 | O26: =IFERROR(SUMIFS(Datos_Dotacion!$K:$K,Datos_Dotacion!$A:$A,$A$4,Datos_Dotacion!$B:$B,$E$4,Datos_Dotacion!$C:$C,10)+SUMIFS(Datos_Dotacion!$L:$L,Datos_Dotacion!$A:$A,$A$4,Datos_Dotacion!$B:$B,$E$4,Datos_Dotacion!$C:$C,10),0) -> 2 | P26: =O26-N26 -> 1 | Q26: =IFERROR(E26/T26/Parametros!$B$7,0) -> 4.3962963 | R26: =IFERROR((IF((IFERROR(SUMIFS(Datos_Vacios!$G:$G,Datos_Vacios!$A:$A,$A$4,Datos_Vacios!$B:$B,$E$4,Datos_Vacios!$C:$C,10,Datos_Vacios!$F:$F,"Sí"),0))>0,(IFERROR(SUMIFS(Datos_Vacios!$G:$G,Datos_Vacios!$A:$A,$A$4,Datos_Vacios!$B:$B,$E$4,Datos_Vacios!$C:$C,10,Datos_Vacios!$F:$F,"Sí"),0)),(IFERROR(SUMIFS(Datos_Vacios!$G:$G,Datos_Vacios!$A:$A,$A$4,Datos_Vacios!$B:$B,$E$4-1,Datos_Vacios!$C:$C,10,Datos_Vacios!$F:$F,"Sí"),0))))*(1+$C$4)/T26/Parametros!$B$8,0) -> 1.7563786 | S26: =IFERROR(C26*(IF($A$4="Casa Central",Tablas_Operativas!B15,Tablas_Operativas!F15))/T26/Parametros!$B$6,0) -> 4.7133827 | T26: =DAY(EOMONTH(DATE($E$4,10,1),0))-SUMPRODUCT((WEEKDAY(DATE($E$4,10,ROW(INDIRECT("1:"&DAY(EOMONTH(DATE($E$4,10,1),0))))),2)=7)*1) -> 27 | U26: =IFERROR((I26*Parametros!$B$14 + J26*Parametros!$B$14 + L26*Parametros!$B$16)/(G26*Parametros!$B$14),0) -> 0.45238095 | V26: =IF(M26<-2,"🔴 CRÍTICO — Contratar "&ABS(M26)&" pickers urgente",IF(M26<0,"🟠 FALTAN "&ABS(M26)&" picker(s) — horas extra o temp.",IF(P26<0,"🟡 FALTAN "&ABS(P26)&" auto(s) — evaluar alquiler",IF(U26>Parametros!$B$13,"🔴 SOBRECARGA "&TEXT(U26,"0%"),IF(U26>Parametros!$B$12,"🟡 RIESGO "&TEXT(U26,"0%"),IF(M26>3,"🟢 OK — evaluar reducir "&(M26-2)&" temp.","🟢 OK")))))) -> 🟢 OK
A27: Noviembre | B27: =IFERROR(IF(SUMIFS(Datos_Volumen!$E:$E,Datos_Volumen!$A:$A,$A$4,Datos_Volumen!$B:$B,$E$4,Datos_Volumen!$C:$C,11)>0,SUMIFS(Datos_Volumen!$E:$E,Datos_Volumen!$A:$A,$A$4,Datos_Volumen!$B:$B,$E$4,Datos_Volumen!$C:$C,11),SUMIFS(Datos_Volumen!$E:$E,Datos_Volumen!$A:$A,$A$4,Datos_Volumen!$B:$B,$E$4-1,Datos_Volumen!$C:$C,11)),0) -> 71645 | C27: =B27*(1+$C$4) -> 78809.5 | D27: =IFERROR(IF(SUMIFS(Datos_Volumen!$F:$F,Datos_Volumen!$A:$A,$A$4,Datos_Volumen!$B:$B,$E$4,Datos_Volumen!$C:$C,11)>0,SUMIFS(Datos_Volumen!$F:$F,Datos_Volumen!$A:$A,$A$4,Datos_Volumen!$B:$B,$E$4,Datos_Volumen!$C:$C,11),SUMIFS(Datos_Volumen!$F:$F,Datos_Volumen!$A:$A,$A$4,Datos_Volumen!$B:$B,$E$4-1,Datos_Volumen!$C:$C,11)),0) -> 6687 | E27: =D27*(1+$C$4) -> 7355.7 | F27: =IFERROR(SUMIFS(Datos_Dotacion!$I:$I,Datos_Dotacion!$A:$A,$A$4,Datos_Dotacion!$B:$B,$E$4,Datos_Dotacion!$C:$C,11),0) -> 10 | G27: =FLOOR(F27*(1-(IFERROR(SUMIFS(Datos_Dotacion!$J:$J,Datos_Dotacion!$A:$A,$A$4,Datos_Dotacion!$B:$B,$E$4,Datos_Dotacion!$C:$C,11),0))),1) -> 9 | H27: =IF($A$4="Casa Central",Tablas_Operativas!B32,Tablas_Operativas!F32) -> 2 | I27: =IFERROR(ROUNDUP((E27/T27/Parametros!$B$7)/Parametros!$B$14,0),0) -> 1 | J27: =IFERROR(ROUNDUP(((IF((IFERROR(SUMIFS(Datos_Vacios!$G:$G,Datos_Vacios!$A:$A,$A$4,Datos_Vacios!$B:$B,$E$4,Datos_Vacios!$C:$C,11,Datos_Vacios!$F:$F,"Sí"),0))>0,(IFERROR(SUMIFS(Datos_Vacios!$G:$G,Datos_Vacios!$A:$A,$A$4,Datos_Vacios!$B:$B,$E$4,Datos_Vacios!$C:$C,11,Datos_Vacios!$F:$F,"Sí"),0)),(IFERROR(SUMIFS(Datos_Vacios!$G:$G,Datos_Vacios!$A:$A,$A$4,Datos_Vacios!$B:$B,$E$4-1,Datos_Vacios!$C:$C,11,Datos_Vacios!$F:$F,"Sí"),0))))*(1+$C$4)/T27/Parametros!$B$8)/Parametros!$B$14,0),0) -> 1 | K27: =MAX(G27-H27-I27-J27,0) -> 5 | L27: =IFERROR(ROUNDUP((C27*(IF($A$4="Casa Central",Tablas_Operativas!B16,Tablas_Operativas!F16))/T27/Parametros!$B$6)/Parametros!$B$16,0),0) -> 2 | M27: =K27-L27 -> 3 | N27: =I27 -> 1 | O27: =IFERROR(SUMIFS(Datos_Dotacion!$K:$K,Datos_Dotacion!$A:$A,$A$4,Datos_Dotacion!$B:$B,$E$4,Datos_Dotacion!$C:$C,11)+SUMIFS(Datos_Dotacion!$L:$L,Datos_Dotacion!$A:$A,$A$4,Datos_Dotacion!$B:$B,$E$4,Datos_Dotacion!$C:$C,11),0) -> 2 | P27: =O27-N27 -> 1 | Q27: =IFERROR(E27/T27/Parametros!$B$7,0) -> 6.687 | R27: =IFERROR((IF((IFERROR(SUMIFS(Datos_Vacios!$G:$G,Datos_Vacios!$A:$A,$A$4,Datos_Vacios!$B:$B,$E$4,Datos_Vacios!$C:$C,11,Datos_Vacios!$F:$F,"Sí"),0))>0,(IFERROR(SUMIFS(Datos_Vacios!$G:$G,Datos_Vacios!$A:$A,$A$4,Datos_Vacios!$B:$B,$E$4,Datos_Vacios!$C:$C,11,Datos_Vacios!$F:$F,"Sí"),0)),(IFERROR(SUMIFS(Datos_Vacios!$G:$G,Datos_Vacios!$A:$A,$A$4,Datos_Vacios!$B:$B,$E$4-1,Datos_Vacios!$C:$C,11,Datos_Vacios!$F:$F,"Sí"),0))))*(1+$C$4)/T27/Parametros!$B$8,0) -> 2.5031111 | S27: =IFERROR(C27*(IF($A$4="Casa Central",Tablas_Operativas!B16,Tablas_Operativas!F16))/T27/Parametros!$B$6,0) -> 7.6421333 | T27: =DAY(EOMONTH(DATE($E$4,11,1),0))-SUMPRODUCT((WEEKDAY(DATE($E$4,11,ROW(INDIRECT("1:"&DAY(EOMONTH(DATE($E$4,11,1),0))))),2)=7)*1) -> 25 | U27: =IFERROR((I27*Parametros!$B$14 + J27*Parametros!$B$14 + L27*Parametros!$B$16)/(G27*Parametros!$B$14),0) -> 0.38095238 | V27: =IF(M27<-2,"🔴 CRÍTICO — Contratar "&ABS(M27)&" pickers urgente",IF(M27<0,"🟠 FALTAN "&ABS(M27)&" picker(s) — horas extra o temp.",IF(P27<0,"🟡 FALTAN "&ABS(P27)&" auto(s) — evaluar alquiler",IF(U27>Parametros!$B$13,"🔴 SOBRECARGA "&TEXT(U27,"0%"),IF(U27>Parametros!$B$12,"🟡 RIESGO "&TEXT(U27,"0%"),IF(M27>3,"🟢 OK — evaluar reducir "&(M27-2)&" temp.","🟢 OK")))))) -> 🟢 OK
A28: Diciembre | B28: =IFERROR(IF(SUMIFS(Datos_Volumen!$E:$E,Datos_Volumen!$A:$A,$A$4,Datos_Volumen!$B:$B,$E$4,Datos_Volumen!$C:$C,12)>0,SUMIFS(Datos_Volumen!$E:$E,Datos_Volumen!$A:$A,$A$4,Datos_Volumen!$B:$B,$E$4,Datos_Volumen!$C:$C,12),SUMIFS(Datos_Volumen!$E:$E,Datos_Volumen!$A:$A,$A$4,Datos_Volumen!$B:$B,$E$4-1,Datos_Volumen!$C:$C,12)),0) -> 126769 | C28: =B28*(1+$C$4) -> 139445.9 | D28: =IFERROR(IF(SUMIFS(Datos_Volumen!$F:$F,Datos_Volumen!$A:$A,$A$4,Datos_Volumen!$B:$B,$E$4,Datos_Volumen!$C:$C,12)>0,SUMIFS(Datos_Volumen!$F:$F,Datos_Volumen!$A:$A,$A$4,Datos_Volumen!$B:$B,$E$4,Datos_Volumen!$C:$C,12),SUMIFS(Datos_Volumen!$F:$F,Datos_Volumen!$A:$A,$A$4,Datos_Volumen!$B:$B,$E$4-1,Datos_Volumen!$C:$C,12)),0) -> 12060 | E28: =D28*(1+$C$4) -> 13266 | F28: =IFERROR(SUMIFS(Datos_Dotacion!$I:$I,Datos_Dotacion!$A:$A,$A$4,Datos_Dotacion!$B:$B,$E$4,Datos_Dotacion!$C:$C,12),0) -> 10 | G28: =FLOOR(F28*(1-(IFERROR(SUMIFS(Datos_Dotacion!$J:$J,Datos_Dotacion!$A:$A,$A$4,Datos_Dotacion!$B:$B,$E$4,Datos_Dotacion!$C:$C,12),0))),1) -> 9 | H28: =IF($A$4="Casa Central",Tablas_Operativas!B33,Tablas_Operativas!F33) -> 2 | I28: =IFERROR(ROUNDUP((E28/T28/Parametros!$B$7)/Parametros!$B$14,0),0) -> 2 | J28: =IFERROR(ROUNDUP(((IF((IFERROR(SUMIFS(Datos_Vacios!$G:$G,Datos_Vacios!$A:$A,$A$4,Datos_Vacios!$B:$B,$E$4,Datos_Vacios!$C:$C,12,Datos_Vacios!$F:$F,"Sí"),0))>0,(IFERROR(SUMIFS(Datos_Vacios!$G:$G,Datos_Vacios!$A:$A,$A$4,Datos_Vacios!$B:$B,$E$4,Datos_Vacios!$C:$C,12,Datos_Vacios!$F:$F,"Sí"),0)),(IFERROR(SUMIFS(Datos_Vacios!$G:$G,Datos_Vacios!$A:$A,$A$4,Datos_Vacios!$B:$B,$E$4-1,Datos_Vacios!$C:$C,12,Datos_Vacios!$F:$F,"Sí"),0))))*(1+$C$4)/T28/Parametros!$B$8)/Parametros!$B$14,0),0) -> 1 | K28: =MAX(G28-H28-I28-J28,0) -> 4 | L28: =IFERROR(ROUNDUP((C28*(IF($A$4="Casa Central",Tablas_Operativas!B17,Tablas_Operativas!F17))/T28/Parametros!$B$6)/Parametros!$B$16,0),0) -> 3 | M28: =K28-L28 -> 1 | N28: =I28 -> 2 | O28: =IFERROR(SUMIFS(Datos_Dotacion!$K:$K,Datos_Dotacion!$A:$A,$A$4,Datos_Dotacion!$B:$B,$E$4,Datos_Dotacion!$C:$C,12)+SUMIFS(Datos_Dotacion!$L:$L,Datos_Dotacion!$A:$A,$A$4,Datos_Dotacion!$B:$B,$E$4,Datos_Dotacion!$C:$C,12),0) -> 4 | P28: =O28-N28 -> 2 | Q28: =IFERROR(E28/T28/Parametros!$B$7,0) -> 11.166667 | R28: =IFERROR((IF((IFERROR(SUMIFS(Datos_Vacios!$G:$G,Datos_Vacios!$A:$A,$A$4,Datos_Vacios!$B:$B,$E$4,Datos_Vacios!$C:$C,12,Datos_Vacios!$F:$F,"Sí"),0))>0,(IFERROR(SUMIFS(Datos_Vacios!$G:$G,Datos_Vacios!$A:$A,$A$4,Datos_Vacios!$B:$B,$E$4,Datos_Vacios!$C:$C,12,Datos_Vacios!$F:$F,"Sí"),0)),(IFERROR(SUMIFS(Datos_Vacios!$G:$G,Datos_Vacios!$A:$A,$A$4,Datos_Vacios!$B:$B,$E$4-1,Datos_Vacios!$C:$C,12,Datos_Vacios!$F:$F,"Sí"),0))))*(1+$C$4)/T28/Parametros!$B$8,0) -> 4.0197531 | S28: =IFERROR(C28*(IF($A$4="Casa Central",Tablas_Operativas!B17,Tablas_Operativas!F17))/T28/Parametros!$B$6,0) -> 12.520395 | T28: =DAY(EOMONTH(DATE($E$4,12,1),0))-SUMPRODUCT((WEEKDAY(DATE($E$4,12,ROW(INDIRECT("1:"&DAY(EOMONTH(DATE($E$4,12,1),0))))),2)=7)*1) -> 27 | U28: =IFERROR((I28*Parametros!$B$14 + J28*Parametros!$B$14 + L28*Parametros!$B$16)/(G28*Parametros!$B$14),0) -> 0.57142857 | V28: =IF(M28<-2,"🔴 CRÍTICO — Contratar "&ABS(M28)&" pickers urgente",IF(M28<0,"🟠 FALTAN "&ABS(M28)&" picker(s) — horas extra o temp.",IF(P28<0,"🟡 FALTAN "&ABS(P28)&" auto(s) — evaluar alquiler",IF(U28>Parametros!$B$13,"🔴 SOBRECARGA "&TEXT(U28,"0%"),IF(U28>Parametros!$B$12,"🟡 RIESGO "&TEXT(U28,"0%"),IF(M28>3,"🟢 OK — evaluar reducir "&(M28-2)&" temp.","🟢 OK")))))) -> 🟢 OK
A29: TOTAL/PROM | B29: =SUM(B17:B28) -> 917255 | C29: =SUM(C17:C28) -> 1008980.5 | D29: =SUM(D17:D28) -> 85537 | E29: =SUM(E17:E28) -> 94090.7 | F29: =AVERAGE(F17:F28) -> 9.0833333 | G29: =AVERAGE(G17:G28) -> 8.0833333 | H29: =AVERAGE(H17:H28) -> 1.4166667 | I29: =AVERAGE(I17:I28) -> 1.5 | J29: =AVERAGE(J17:J28) -> 1 | K29: =AVERAGE(K17:K28) -> 4.1666667 | L29: =AVERAGE(L17:L28) -> 1.9166667 | M29: =AVERAGE(M17:M28) -> 2.25 | N29: =MAX(N17:N28) -> 4 | O29: =MIN(O17:O28) -> 2 | P29: =MIN(P17:P28) -> 0 | Q29: =AVERAGE(Q17:Q28) -> 6.8526018 | R29: =AVERAGE(R17:R28) -> 2.2892431 | S29: =AVERAGE(S17:S28) -> 7.8428018 | T29: =AVERAGE(T17:T28) -> 26.083333 | U29: =IFERROR(AVERAGE(U17:U28),0) -> 0.49586835
A31: 📐 FÓRMULA DIARIA: Auto.Req=ROUNDUP(HL/días/44/7hs) | Clasif.Req=ROUNDUP(Pallets/días/4.5/7hs) | Pick.Req=ROUNDUP(Bultos×%pick/días/330/5hs.netas) | Días=días.mes−domingos
A33: 📊 ANÁLISIS VISUAL
A34: Gráfico 1 — CASCADA: Verde=presupuestados / Azul=pool pickers / Rojo=pickers necesarios. Si rojo > azul → faltan pickers ese mes.
A35: Gráfico 2 — BRECHA PICKING: Positivo=sobran pickers / Negativo=faltan. Meses bajo cero requieren acción inmediata.
A36: Gráfico 3 — % UTILIZACIÓN: (Hs.auto/día + Hs.clasif/día + Hs.pick/día) ÷ 7hs. Zona óptima 85–95%. >100% = sobrecarga.
A37: Gráfico 4 — AUTOELEVADORES: Naranja=requeridos por día / Verde=disponibles. Si naranja > verde → alquilar equipo adicional.
A76: 📖 GUÍA DE LECTURA — MODELO CASCADA DIARIA
A77: 🟢 OK | B77: Pool pickers cubre lo necesario. Sin acción.
A78: 🟢 OK — reducir | B78: Sobran >3 pickers. Evaluar reducir temporarios para bajar costo.
A79: 🟡 RIESGO | B79: Utilización >95%. Monitorear. Considerar refuerzo.
A80: 🟠 FALTAN pickers | B80: Brecha negativa leve. Redistribuir turnos u horas extra.
A81: 🔴 CRÍTICO | B81: Faltan >2 pickers. Contratar temporarios urgente.
A82: 🟡 FALTAN autos | B82: Autoelevadores insuficientes. Evaluar alquiler de equipo.
A83: 🔴 SOBRECARGA | B83: Utilización >100%. Riesgo operativo. Acción inmediata.
A84: DÍAS TRABAJADOS | B84: Días del mes − domingos. Calculado automáticamente por año/mes.
A85: AUTO REQ./DÍA | B85: ROUNDUP(HL.ajust ÷ días ÷ 44HL/hs ÷ 7hs/día). Cuántos autos corriendo simultáneamente.
A86: CLASIF. REQ. | B86: ROUNDUP(Pallets.vac ÷ días ÷ 4.5pal/hs ÷ 7hs/día). Del pool, antes que pickers.
A87: PICKERS NECES. | B87: ROUNDUP(Bultos×%pick ÷ días ÷ 330bul/hs ÷ 5hs.netas). 7hs − 2hs otras = 5hs para picking.
A88: POOL PICKERS | B88: Disp.Neto − Controladores − Autoelevadoristas − Clasificadores.
A89: BRECHA PICKING | B89: Pool − Pickers.Neces. Positivo=sobra / Negativo=falta. Todo en enteros.

Sheet Tablas_Operativas
A1: 📋 TABLAS OPERATIVAS — Editar mensualmente
A2: Celdas AMARILLAS son editables. El Dashboard las toma automáticamente.
A4: TABLA A — % DE BULTOS QUE VAN A PICKING (el resto = autoelevador directo)
A5: MES | B5: % PICKING CC | C5: % AUTO CC | E5: MES | F5: % PICKING DOL | G5: % AUTO DOL
A6: Enero | B6: 0.8 | C6: =1-B6 -> 0.2 | E6: Enero | F6: 0.6 | G6: =1-F6 -> 0.4
A7: Febrero | B7: 0.8 | C7: =1-B7 -> 0.2 | E7: Febrero | F7: 0.6 | G7: =1-F7 -> 0.4
A8: Marzo | B8: 0.8 | C8: =1-B8 -> 0.2 | E8: Marzo | F8: 0.6 | G8: =1-F8 -> 0.4
A9: Abril | B9: 0.8 | C9: =1-B9 -> 0.2 | E9: Abril | F9: 0.6 | G9: =1-F9 -> 0.4
A10: Mayo | B10: 0.8 | C10: =1-B10 -> 0.2 | E10: Mayo | F10: 0.6 | G10: =1-F10 -> 0.4
A11: Junio | B11: 0.8 | C11: =1-B11 -> 0.2 | E11: Junio | F11: 0.6 | G11: =1-F11 -> 0.4
A12: Julio | B12: 0.8 | C12: =1-B12 -> 0.2 | E12: Julio | F12: 0.6 | G12: =1-F12 -> 0.4
A13: Agosto | B13: 0.8 | C13: =1-B13 -> 0.2 | E13: Agosto | F13: 0.6 | G13: =1-F13 -> 0.4
A14: Septiembre | B14: 0.8 | C14: =1-B14 -> 0.2 | E14: Septiembre | F14: 0.6 | G14: =1-F14 -> 0.4
A15: Octubre | B15: 0.8 | C15: =1-B15 -> 0.2 | E15: Octubre | F15: 0.6 | G15: =1-F15 -> 0.4
A16: Noviembre | B16: 0.8 | C16: =1-B16 -> 0.2 | E16: Noviembre | F16: 0.6 | G16: =1-F16 -> 0.4
A17: Diciembre | B17: 0.8 | C17: =1-B17 -> 0.2 | E17: Diciembre | F17: 0.6 | G17: =1-F17 -> 0.4
A18: ℹ El % auto = bultos movidos por autoelevador directo, sin picker. No afecta cálculo de autos (los autos se calculan por HL, no por bultos).
A20: TABLA B — CONTROLADORES POR MES (se restan del pool al inicio de la cascada)
A21: MES | B21: CTRL CC | C21: REFERENCIA | E21: MES | F21: CTRL DOL | G21: REFERENCIA
A22: Enero | B22: 2 | C22: Editar según plan | E22: Enero | F22: 1 | G22: Editar según plan
A23: Febrero | B23: 2 | C23: Editar según plan | E23: Febrero | F23: 1 | G23: Editar según plan
A24: Marzo | B24: 1 | C24: Editar según plan | E24: Marzo | F24: 1 | G24: Editar según plan
A25: Abril | B25: 1 | C25: Editar según plan | E25: Abril | F25: 1 | G25: Editar según plan
A26: Mayo | B26: 1 | C26: Editar según plan | E26: Mayo | F26: 1 | G26: Editar según plan
A27: Junio | B27: 1 | C27: Editar según plan | E27: Junio | F27: 1 | G27: Editar según plan
A28: Julio | B28: 1 | C28: Editar según plan | E28: Julio | F28: 1 | G28: Editar según plan
A29: Agosto | B29: 1 | C29: Editar según plan | E29: Agosto | F29: 1 | G29: Editar según plan
A30: Septiembre | B30: 1 | C30: Editar según plan | E30: Septiembre | F30: 1 | G30: Editar según plan
A31: Octubre | B31: 2 | C31: Editar según plan | E31: Octubre | F31: 1 | G31: Editar según plan
A32: Noviembre | B32: 2 | C32: Editar según plan | E32: Noviembre | F32: 1 | G32: Editar según plan
A33: Diciembre | B33: 2 | C33: Editar según plan | E33: Diciembre | F33: 1 | G33: Editar según plan
A34: ℹ Controladores: primeros en descontarse. No clasifican ni pickean.

Sheet Parametros
A1: Parámetro | B1: Valor | C1: Unidad | D1: Descripción | F1: Escenarios | H1: Sucursales | J1: Años | L1: Meses
A2: Sucursal seleccionada | B2: Casa Central | D2: Usar lista desplegable: Casa Central o Dolores | F2: -0.3 | H2: Casa Central | J2: 2025 | L2: Enero
A3: Año seleccionado | B3: 2026 | D3: Usar lista desplegable: 2025 o 2026 | F3: -0.25 | H3: Dolores | J3: 2026 | L3: Febrero
A4: Mes seleccionado | B4: Enero | D4: Mes mostrado en tarjetas principales | F4: -0.2 | L4: Marzo
A5: Escenario venta | B5: 0 | C5: % | D5: Impacta todos los volúmenes: bultos, HL, pallets y vacíos | F5: -0.15 | L5: Abril
A6: Productividad objetivo Picking | B6: 330 | C6: bultos/hora | D6: Bultos procesados por hora | F6: -0.1 | L6: Mayo
A7: Productividad objetivo Autoelevador | B7: 44 | C7: HL/hora | D7: FNP objetivo | F7: -0.05 | L7: Junio
A8: Productividad objetivo Vacíos | B8: 4.5 | C8: pallets/hora | D8: Clasificación de vacíos | F8: 0 | L8: Julio
A9: Horas mensuales por operario | B9: =7*25 -> 175 | C9: HH/persona | D9: Capacidad teórica mensual por persona | F9: 0.05 | L9: Agosto
A10: Horas mensuales por autoelevador | B10: =6*25 -> 150 | C10: HH/MHE | D10: Capacidad mensual por equipo | F10: 0.1 | L10: Septiembre
A11: Umbral sobrecapacidad | B11: 0.85 | C11: % uso HH | D11: Menor a este valor indica posible sobrecapacidad | F11: 0.15 | L11: Octubre
A12: Umbral riesgo | B12: 0.95 | C12: % uso HH | D12: Mayor a este valor indica riesgo operativo | F12: 0.2 | L12: Noviembre
A13: Umbral falta personal | B13: 1 | C13: % uso HH | D13: Mayor a este valor indica falta de personal | F13: 0.25 | L13: Diciembre
A14: Horas efectivas/día | B14: 7 | C14: hs/día | D14: 8 hs turno − 1 hs almuerzo = 7 hs efectivas (aplica a todas las tareas) | F14: 0.3
A15: Horas otras tareas/día | B15: 2 | C15: hs/día | D15: Tareas no picking que descuentan del turno del picker (7−2=5 hs netas picking)
A16: Horas netas picking/día | B16: =B14-B15 -> 5 | C16: hs/día | D16: Horas efectivas para picking (7 − 2 otras = 5 hs)

Sheet Datos_Volumen
A1: Sucursal | B1: Año | C1: Mes Nro | D1: Mes | E1: Bultos base | F1: HL base | G1: Pallets base
A2: Casa Central | B2: 2025 | C2: 1 | D2: Enero | E2: 287440 | F2: 25909 | G2: 2726
A3: Casa Central | B3: 2025 | C3: 2 | D3: Febrero | E3: 193652 | F3: 16628 | G3: 1853
A4: Casa Central | B4: 2025 | C4: 3 | D4: Marzo | E4: 59793 | F4: 5508 | G4: 628
A5: Casa Central | B5: 2025 | C5: 4 | D5: Abril | E5: 39969 | F5: 3733 | G5: 426
A6: Casa Central | B6: 2025 | C6: 5 | D6: Mayo | E6: 34697 | F6: 3603 | G6: 401
A7: Casa Central | B7: 2025 | C7: 6 | D7: Junio | E7: 30400 | F7: 2984 | G7: 321
A8: Casa Central | B8: 2025 | C8: 7 | D8: Julio | E8: 39209 | F8: 3858 | G8: 417
A9: Casa Central | B9: 2025 | C9: 8 | D9: Agosto | E9: 40289 | F9: 4028 | G9: 448
A10: Casa Central | B10: 2025 | C10: 9 | D10: Septiembre | E10: 23148 | F10: 2117 | G10: 236
A11: Casa Central | B11: 2025 | C11: 10 | D11: Octubre | E11: 47723 | F11: 4748 | G11: 544
A12: Casa Central | B12: 2025 | C12: 11 | D12: Noviembre | E12: 71645 | F12: 6687 | G12: 746
A13: Casa Central | B13: 2025 | C13: 12 | D13: Diciembre | E13: 126769 | F13: 12060 | G13: 1333
A14: Casa Central | B14: 2026 | C14: 1 | D14: Enero | E14: 252960 | F14: 22766 | G14: 2435 | I14: =252000*0.8 -> 201600 | J14: =+I14/26 -> 7753.8462 | K14: =+J14/5 -> 1550.7692 | L14: =+K14/330 -> 4.6993007
A15: Casa Central | B15: 2026 | C15: 2 | D15: Febrero | E15: 177249 | F15: 15895 | G15: 1707
A16: Casa Central | B16: 2026 | C16: 3 | D16: Marzo | E16: 54213 | F16: 5113 | G16: 574
A17: Casa Central | B17: 2026 | C17: 4 | D17: Abril | E17: 30159 | F17: 2922 | G17: 337
A18: Casa Central | B18: 2026 | C18: 5 | D18: Mayo | E18: 23491 | F18: 2359 | G18: 269
A19: Casa Central | B19: 2026 | C19: 6 | D19: Junio
A20: Casa Central | B20: 2026 | C20: 7 | D20: Julio
A21: Casa Central | B21: 2026 | C21: 8 | D21: Agosto
A22: Casa Central | B22: 2026 | C22: 9 | D22: Septiembre
A23: Casa Central | B23: 2026 | C23: 10 | D23: Octubre
A24: Casa Central | B24: 2026 | C24: 11 | D24: Noviembre
A25: Casa Central | B25: 2026 | C25: 12 | D25: Diciembre
A26: Dolores | B26: 2025 | C26: 1 | D26: Enero | E26: 42230 | F26: 3700 | G26: 396
A27: Dolores | B27: 2025 | C27: 2 | D27: Febrero | E27: 35955 | F27: 3068 | G27: 338
A28: Dolores | B28: 2025 | C28: 3 | D28: Marzo | E28: 26082 | F28: 2490 | G28: 277
A29: Dolores | B29: 2025 | C29: 4 | D29: Abril | E29: 23558 | F29: 2263 | G29: 247
A30: Dolores | B30: 2025 | C30: 5 | D30: Mayo | E30: 22146 | F30: 2166 | G30: 229
A31: Dolores | B31: 2025 | C31: 6 | D31: Junio | E31: 16683 | F31: 1606 | G31: 172
A32: Dolores | B32: 2025 | C32: 7 | D32: Julio | E32: 21228 | F32: 1978 | G32: 208
A33: Dolores | B33: 2025 | C33: 8 | D33: Agosto | E33: 21998 | F33: 2062 | G33: 234
A34: Dolores | B34: 2025 | C34: 9 | D34: Septiembre | E34: 23148 | F34: 2117 | G34: 236
A35: Dolores | B35: 2025 | C35: 10 | D35: Octubre | E35: 26985 | F35: 2523 | G35: 281
A36: Dolores | B36: 2025 | C36: 11 | D36: Noviembre | E36: 27054 | F36: 2417 | G36: 273
A37: Dolores | B37: 2025 | C37: 12 | D37: Diciembre | E37: 39767 | F37: 3704 | G37: 424
... A42: Dolores | B42: 2026 | C42: 5 | D42: Mayo | E42: 21654 | F42: 2109 | G42: 224
A43: Dolores | B43: 2026 | C43: 6 | D43: Junio
A44: Dolores | B44: 2026 | C44: 7 | D44: Julio
A45: Dolores | B45: 2026 | C45: 8 | D45: Agosto
A46: Dolores | B46: 2026 | C46: 9 | D46: Septiembre
A47: Dolores | B47: 2026 | C47: 10 | D47: Octubre
A48: Dolores | B48: 2026 | C48: 11 | D48: Noviembre
A49: Dolores | B49: 2026 | C49: 12 | D49: Diciembre

Sheet Datos_Dotacion
A1: Sucursal | B1: Año | C1: Mes Nro | D1: Mes | E1: Operarios fijos planificados | F1: Operarios temporarios planificados | G1: Operarios fijos reales | H1: Operarios temporarios reales | I1: Operarios planificados totales | J1: Ausentismo % | K1: Autoelevadores propios | L1: Autoelevadores alquilados | M1: Autoelevadores disponibles
A2: Casa Central | B2: 2025 | C2: 1 | D2: Enero | E2: 6 | F2: 12 | G2: 6 | H2: 12 | I2: =+tblDotacion[[#This Row],[Operarios fijos planificados]]+tblDotacion[[#This Row],[Operarios temporarios planificados]] -> 18 | J2: 0.0302 | K2: 2 | L2: 2 | M2: =+tblDotacion[[#This Row],[Autoelevadores propios]]+tblDotacion[[#This Row],[Autoelevadores alquilados]] -> 4
A3: Casa Central | B3: 2025 | C3: 2 | D3: Febrero | E3: 6 | F3: 12 | G3: 6 | H3: 12 | I3: =+tblDotacion[[#This Row],[Operarios fijos planificados]]+tblDotacion[[#This Row],[Operarios temporarios planificados]] -> 18 | J3: 0.0565 | K3: 2 | L3: 2 | M3: =+tblDotacion[[#This Row],[Autoelevadores propios]]+tblDotacion[[#This Row],[Autoelevadores alquilados]] -> 4
A4: Casa Central | B4: 2025 | C4: 3 | D4: Marzo | E4: 6 | F4: 4 | G4: 6 | H4: 4 | I4: =+tblDotacion[[#This Row],[Operarios fijos planificados]]+tblDotacion[[#This Row],[Operarios temporarios planificados]] -> 10 | J4: 0.16 | K4: 2 | L4: 0 | M4: =+tblDotacion[[#This Row],[Autoelevadores propios]]+tblDotacion[[#This Row],[Autoelevadores alquilados]] -> 2
A5: Casa Central | B5: 2025 | C5: 4 | D5: Abril | E5: 6 | F5: 0 | I5: =+tblDotacion[[#This Row],[Operarios fijos planificados]]+tblDotacion[[#This Row],[Operarios temporarios planificados]] -> 6 | J5: 0.1558 | K5: 2 | L5: 0 | M5: =+tblDotacion[[#This Row],[Autoelevadores propios]]+tblDotacion[[#This Row],[Autoelevadores alquilados]] -> 2
A6: Casa Central | B6: 2025 | C6: 5 | D6: Mayo | E6: 6 | F6: 0 | I6: =+tblDotacion[[#This Row],[Operarios fijos planificados]]+tblDotacion[[#This Row],[Operarios temporarios planificados]] -> 6 | J6: 0.028 | K6: 2 | L6: 0 | M6: =+tblDotacion[[#This Row],[Autoelevadores propios]]+tblDotacion[[#This Row],[Autoelevadores alquilados]] -> 2
A7: Casa Central | B7: 2025 | C7: 6 | D7: Junio | E7: 6 | F7: 0 | I7: =+tblDotacion[[#This Row],[Operarios fijos planificados]]+tblDotacion[[#This Row],[Operarios temporarios planificados]] -> 6 | J7: 0.0119 | K7: 2 | L7: 0 | M7: =+tblDotacion[[#This Row],[Autoelevadores propios]]+tblDotacion[[#This Row],[Autoelevadores alquilados]] -> 2
A8: Casa Central | B8: 2025 | C8: 7 | D8: Julio | E8: 6 | F8: 0 | I8: =+tblDotacion[[#This Row],[Operarios fijos planificados]]+tblDotacion[[#This Row],[Operarios temporarios planificados]] -> 6 | J8: 0.021 | K8: 2 | L8: 0 | M8: =+tblDotacion[[#This Row],[Autoelevadores propios]]+tblDotacion[[#This Row],[Autoelevadores alquilados]] -> 2
A9: Casa Central | B9: 2025 | C9: 8 | D9: Agosto | E9: 6 | F9: 0 | I9: =+tblDotacion[[#This Row],[Operarios fijos planificados]]+tblDotacion[[#This Row],[Operarios temporarios planificados]] -> 6 | J9: 0.0269 | K9: 2 | L9: 0 | M9: =+tblDotacion[[#This Row],[Autoelevadores propios]]+tblDotacion[[#This Row],[Autoelevadores alquilados]] -> 2
A10: Casa Central | B10: 2025 | C10: 9 | D10: Septiembre | E10: 6 | F10: 0 | I10: =+tblDotacion[[#This Row],[Operarios fijos planificados]]+tblDotacion[[#This Row],[Operarios temporarios planificados]] -> 6 | J10: 0.0346 | K10: 2 | L10: 0 | M10: =+tblDotacion[[#This Row],[Autoelevadores propios]]+tblDotacion[[#This Row],[Autoelevadores alquilados]] -> 2
A11: Casa Central | B11: 2025 | C11: 10 | D11: Octubre | E11: 6 | F11: 1 | I11: =+tblDotacion[[#This Row],[Operarios fijos planificados]]+tblDotacion[[#This Row],[Operarios temporarios planificados]] -> 7 | J11: 0.1294 | K11: 2 | L11: 0 | M11: =+tblDotacion[[#This Row],[Autoelevadores propios]]+tblDotacion[[#This Row],[Autoelevadores alquilados]] -> 2
A12: Casa Central | B12: 2025 | C12: 11 | D12: Noviembre | E12: 6 | F12: 4 | I12: =+tblDotacion[[#This Row],[Operarios fijos planificados]]+tblDotacion[[#This Row],[Operarios temporarios planificados]] -> 10 | J12: 0.0682 | K12: 2 | L12: 0 | M12: =+tblDotacion[[#This Row],[Autoelevadores propios]]+tblDotacion[[#This Row],[Autoelevadores alquilados]] -> 2
A13: Casa Central | B13: 2025 | C13: 12 | D13: Diciembre | E13: 6 | F13: 4 | I13: =+tblDotacion[[#This Row],[Operarios fijos planificados]]+tblDotacion[[#This Row],[Operarios temporarios planificados]] -> 10 | J13: 0.1333 | K13: 2 | L13: 2 | M13: =+tblDotacion[[#This Row],[Autoelevadores propios]]+tblDotacion[[#This Row],[Autoelevadores alquilados]] -> 4
A14: Casa Central | B14: 2026 | C14: 1 | D14: Enero | E14: 6 | F14: 12 | G14: 6 | H14: 12 | I14: =+tblDotacion[[#This Row],[Operarios fijos planificados]]+tblDotacion[[#This Row],[Operarios temporarios planificados]] -> 18 | J14: 0.0272 | K14: 2 | L14: 2 | M14: =+tblDotacion[[#This Row],[Autoelevadores propios]]+tblDotacion[[#This Row],[Autoelevadores alquilados]] -> 4
A15: Casa Central | B15: 2026 | C15: 2 | D15: Febrero | E15: 6 | F15: 12 | G15: 6 | H15: 12 | I15: =+tblDotacion[[#This Row],[Operarios fijos planificados]]+tblDotacion[[#This Row],[Operarios temporarios planificados]] -> 18 | J15: 0.0342 | K15: 2 | L15: 2 | M15: =+tblDotacion[[#This Row],[Autoelevadores propios]]+tblDotacion[[#This Row],[Autoelevadores alquilados]] -> 4
A16: Casa Central | B16: 2026 | C16: 3 | D16: Marzo | E16: 6 | F16: 4 | G16: 6 | H16: 4 | I16: =+tblDotacion[[#This Row],[Operarios fijos planificados]]+tblDotacion[[#This Row],[Operarios temporarios planificados]] -> 10 | J16: 0.033 | K16: 2 | L16: 0 | M16: =+tblDotacion[[#This Row],[Autoelevadores propios]]+tblDotacion[[#This Row],[Autoelevadores alquilados]] -> 2
A17: Casa Central | B17: 2026 | C17: 4 | D17: Abril | E17: 6 | F17: 0 | I17: =+tblDotacion[[#This Row],[Operarios fijos planificados]]+tblDotacion[[#This Row],[Operarios temporarios planificados]] -> 6 | J17: 0.0587 | K17: 2 | L17: 0 | M17: =+tblDotacion[[#This Row],[Autoelevadores propios]]+tblDotacion[[#This Row],[Autoelevadores alquilados]] -> 2
A18: Casa Central | B18: 2026 | C18: 5 | D18: Mayo | E18: 6 | F18: 0 | I18: =+tblDotacion[[#This Row],[Operarios fijos planificados]]+tblDotacion[[#This Row],[Operarios temporarios planificados]] -> 6 | J18: 0.0383 | K18: 2 | L18: 0 | M18: =+tblDotacion[[#This Row],[Autoelevadores propios]]+tblDotacion[[#This Row],[Autoelevadores alquilados]] -> 2
A19: Casa Central | B19: 2026 | C19: 6 | D19: Junio | E19: 6 | F19: 0 | I19: =+tblDotacion[[#This Row],[Operarios fijos planificados]]+tblDotacion[[#This Row],[Operarios temporarios planificados]] -> 6 | J19: 0.0383 | K19: 2 | L19: 0 | M19: =+tblDotacion[[#This Row],[Autoelevadores propios]]+tblDotacion[[#This Row],[Autoelevadores alquilados]] -> 2
A20: Casa Central | B20: 2026 | C20: 7 | D20: Julio | E20: 6 | F20: 0 | I20: =+tblDotacion[[#This Row],[Operarios fijos planificados]]+tblDotacion[[#This Row],[Operarios temporarios planificados]] -> 6 | J20: 0.0383 | K20: 2 | L20: 0 | M20: =+tblDotacion[[#This Row],[Autoelevadores propios]]+tblDotacion[[#This Row],[Autoelevadores alquilados]] -> 2
A21: Casa Central | B21: 2026 | C21: 8 | D21: Agosto | E21: 6 | F21: 0 | I21: =+tblDotacion[[#This Row],[Operarios fijos planificados]]+tblDotacion[[#This Row],[Operarios temporarios planificados]] -> 6 | J21: 0.0383 | K21: 2 | L21: 0 | M21: =+tblDotacion[[#This Row],[Autoelevadores propios]]+tblDotacion[[#This Row],[Autoelevadores alquilados]] -> 2
A22: Casa Central | B22: 2026 | C22: 9 | D22: Septiembre | E22: 6 | F22: 0 | I22: =+tblDotacion[[#This Row],[Operarios fijos planificados]]+tblDotacion[[#This Row],[Operarios temporarios planificados]] -> 6 | J22: 0.0383 | K22: 2 | L22: 0 | M22: =+tblDotacion[[#This Row],[Autoelevadores propios]]+tblDotacion[[#This Row],[Autoelevadores alquilados]] -> 2
A23: Casa Central | B23: 2026 | C23: 10 | D23: Octubre | E23: 6 | F23: 1 | I23: =+tblDotacion[[#This Row],[Operarios fijos planificados]]+tblDotacion[[#This Row],[Operarios temporarios planificados]] -> 7 | J23: 0.0383 | K23: 2 | L23: 0 | M23: =+tblDotacion[[#This Row],[Autoelevadores propios]]+tblDotacion[[#This Row],[Autoelevadores alquilados]] -> 2
A24: Casa Central | B24: 2026 | C24: 11 | D24: Noviembre | E24: 6 | F24: 4 | I24: =+tblDotacion[[#This Row],[Operarios fijos planificados]]+tblDotacion[[#This Row],[Operarios temporarios planificados]] -> 10 | J24: 0.0383 | K24: 2 | L24: 0 | M24: =+tblDotacion[[#This Row],[Autoelevadores propios]]+tblDotacion[[#This Row],[Autoelevadores alquilados]] -> 2
A25: Casa Central | B25: 2026 | C25: 12 | D25: Diciembre | E25: 6 | F25: 4 | I25: =+tblDotacion[[#This Row],[Operarios fijos planificados]]+tblDotacion[[#This Row],[Operarios temporarios planificados]] -> 10 | J25: 0.0383 | K25: 2 | L25: 2 | M25: =+tblDotacion[[#This Row],[Autoelevadores propios]]+tblDotacion[[#This Row],[Autoelevadores alquilados]] -> 4
A26: Dolores | B26: 2025 | C26: 1 | D26: Enero | E26: 2 | F26: 0 | I26: =+tblDotacion[[#This Row],[Operarios fijos planificados]]+tblDotacion[[#This Row],[Operarios temporarios planificados]] -> 2 | J26: 0.0302 | K26: 1 | L26: 0 | M26: =+tblDotacion[[#This Row],[Autoelevadores propios]]+tblDotacion[[#This Row],[Autoelevadores alquilados]] -> 1
A27: Dolores | B27: 2025 | C27: 2 | D27: Febrero | E27: 2 | F27: 0 | I27: =+tblDotacion[[#This Row],[Operarios fijos planificados]]+tblDotacion[[#This Row],[Operarios temporarios planificados]] -> 2 | J27: 0.0565 | K27: 1 | L27: 0 | M27: =+tblDotacion[[#This Row],[Autoelevadores propios]]+tblDotacion[[#This Row],[Autoelevadores alquilados]] -> 1
A28: Dolores | B28: 2025 | C28: 3 | D28: Marzo | E28: 2 | F28: 0 | I28: =+tblDotacion[[#This Row],[Operarios fijos planificados]]+tblDotacion[[#This Row],[Operarios temporarios planificados]] -> 2 | J28: 0.16 | K28: 1 | L28: 0 | M28: =+tblDotacion[[#This Row],[Autoelevadores propios]]+tblDotacion[[#This Row],[Autoelevadores alquilados]] -> 1
... A49: Dolores | B49: 2026 | C49: 12 | D49: Diciembre | E49: 2 | F49: 0 | I49: =+tblDotacion[[#This Row],[Operarios fijos planificados]]+tblDotacion[[#This Row],[Operarios temporarios planificados]] -> 2 | J49: 0.0383 | K49: 1 | L49: 0 | M49: =+tblDotacion[[#This Row],[Autoelevadores propios]]+tblDotacion[[#This Row],[Autoelevadores alquilados]] -> 1

Sheet Datos_Vacios
A1: Sucursal | B1: Año | C1: Mes Nro | D1: Mes | E1: Calibre | F1: Participa en vacíos | G1: Pallets vendidos
A2: Casa Central | B2: 2025 | C2: 1 | D2: Enero | E2: 1 L | F2: Sí | G2: 590
A3: Casa Central | B3: 2025 | C3: 2 | D3: Febrero | E3: 1 L | F3: Sí | G3: 457
A4: Casa Central | B4: 2025 | C4: 3 | D4: Marzo | E4: 1 L | F4: Sí | G4: 210
A5: Casa Central | B5: 2025 | C5: 4 | D5: Abril | E5: 1 L | F5: Sí | G5: 148
A6: Casa Central | B6: 2025 | C6: 5 | D6: Mayo | E6: 1 L | F6: Sí | G6: 144
A7: Casa Central | B7: 2025 | C7: 6 | D7: Junio | E7: 1 L | F7: Sí | G7: 87
A8: Casa Central | B8: 2025 | C8: 7 | D8: Julio | E8: 1 L | F8: Sí | G8: 102
A9: Casa Central | B9: 2025 | C9: 8 | D9: Agosto | E9: 1 L | F9: Sí | G9: 130
A10: Casa Central | B10: 2025 | C10: 9 | D10: Septiembre | E10: 1 L | F10: Sí | G10: 65
A11: Casa Central | B11: 2025 | C11: 10 | D11: Octubre | E11: 1 L | F11: Sí | G11: 166
A12: Casa Central | B12: 2025 | C12: 11 | D12: Noviembre | E12: 1 L | F12: Sí | G12: 215
A13: Casa Central | B13: 2025 | C13: 12 | D13: Diciembre | E13: 1 L | F13: Sí | G13: 364
... A30: Casa Central | B30: 2026 | C30: 5 | D30: Mayo | E30: 1 L | F30: Sí | G30: 90
A31: Casa Central | B31: 2026 | C31: 6 | D31: Junio | E31: 1 L | F31: Sí
A32: Casa Central | B32: 2026 | C32: 7 | D32: Julio | E32: 1 L | F32: Sí
A33: Casa Central | B33: 2026 | C33: 8 | D33: Agosto | E33: 1 L | F33: Sí
A34: Casa Central | B34: 2026 | C34: 9 | D34: Septiembre | E34: 1 L | F34: Sí
A35: Casa Central | B35: 2026 | C35: 10 | D35: Octubre | E35: 1 L | F35: Sí
A36: Casa Central | B36: 2026 | C36: 11 | D36: Noviembre | E36: 1 L | F36: Sí
A37: Casa Central | B37: 2026 | C37: 12 | D37: Diciembre | E37: 1 L | F37: Sí
A38: Casa Central | B38: 2026 | C38: 1 | D38: Enero | E38: 975 ml | F38: Sí | G38: 186
A39: Casa Central | B39: 2026 | C39: 2 | D39: Febrero | E39: 975 ml | F39: Sí | G39: 130
A40: Casa Central | B40: 2026 | C40: 3 | D40: Marzo | E40: 975 ml | F40: Sí | G40: 33
A41: Casa Central | B41: 2026 | C41: 4 | D41: Abril | E41: 975 ml | F41: Sí | G41: 14
A42: Casa Central | B42: 2026 | C42: 5 | D42: Mayo | E42: 975 ml | F42: Sí | G42: 10
A43: Casa Central | B43: 2026 | C43: 6 | D43: Junio | E43: 975 ml | F43: Sí
A44: Casa Central | B44: 2026 | C44: 7 | D44: Julio | E44: 975 ml | F44: Sí
A45: Casa Central | B45: 2026 | C45: 8 | D45: Agosto | E45: 975 ml | F45: Sí
A46: Casa Central | B46: 2026 | C46: 9 | D46: Septiembre | E46: 975 ml | F46: Sí
A47: Casa Central | B47: 2026 | C47: 10 | D47: Octubre | E47: 975 ml | F47: Sí
A48: Casa Central | B48: 2026 | C48: 11 | D48: Noviembre | E48: 975 ml | F48: Sí
A49: Casa Central | B49: 2026 | C49: 12 | D49: Diciembre | E49: 975 ml | F49: Sí
A50: Dolores | B50: 2025 | C50: 1 | D50: Enero | E50: 1 L | F50: Sí | G50: 94
A51: Dolores | B51: 2025 | C51: 2 | D51: Febrero | E51: 1 L | F51: Sí | G51: 92
A52: Dolores | B52: 2025 | C52: 3 | D52: Marzo | E52: 1 L | F52: Sí | G52: 81
A53: Dolores | B53: 2025 | C53: 4 | D53: Abril | E53: 1 L | F53: Sí | G53: 67
A54: Dolores | B54: 2025 | C54: 5 | D54: Mayo | E54: 1 L | F54: Sí | G54: 50
A55: Dolores | B55: 2025 | C55: 6 | D55: Junio | E55: 1 L | F55: Sí | G55: 35
A56: Dolores | B56: 2025 | C56: 7 | D56: Julio | E56: 1 L | F56: Sí | G56: 38
A57: Dolores | B57: 2025 | C57: 8 | D57: Agosto | E57: 1 L | F57: Sí | G57: 70
A58: Dolores | B58: 2025 | C58: 9 | D58: Septiembre | E58: 1 L | F58: Sí | G58: 65
A59: Dolores | B59: 2025 | C59: 10 | D59: Octubre | E59: 1 L | F59: Sí | G59: 78
A60: Dolores | B60: 2025 | C60: 11 | D60: Noviembre | E60: 1 L | F60: Sí | G60: 82
A61: Dolores | B61: 2025 | C61: 12 | D61: Diciembre | E61: 1 L | F61: Sí | G61: 141
... A78: Dolores | B78: 2026 | C78: 5 | D78: Mayo | E78: 1 L | F78: Sí | G78: 57
A79: Dolores | B79: 2026 | C79: 6 | D79: Junio | E79: 1 L | F79: Sí
A80: Dolores | B80: 2026 | C80: 7 | D80: Julio | E80: 1 L | F80: Sí
A81: Dolores | B81: 2026 | C81: 8 | D81: Agosto | E81: 1 L | F81: Sí
A82: Dolores | B82: 2026 | C82: 9 | D82: Septiembre | E82: 1 L | F82: Sí
A83: Dolores | B83: 2026 | C83: 10 | D83: Octubre | E83: 1 L | F83: Sí
A84: Dolores | B84: 2026 | C84: 11 | D84: Noviembre | E84: 1 L | F84: Sí
A85: Dolores | B85: 2026 | C85: 12 | D85: Diciembre | E85: 1 L | F85: Sí
A86: Dolores | B86: 2026 | C86: 1 | D86: Enero | E86: 975 ml | F86: Sí | G86: 11
A87: Dolores | B87: 2026 | C87: 2 | D87: Febrero | E87: 975 ml | F87: Sí | G87: 10
A88: Dolores | B88: 2026 | C88: 3 | D88: Marzo | E88: 975 ml | F88: Sí | G88: 8
A89: Dolores | B89: 2026 | C89: 4 | D89: Abril | E89: 975 ml | F89: Sí | G89: 7
A90: Dolores | B90: 2026 | C90: 5 | D90: Mayo | E90: 975 ml | F90: Sí | G90: 5
A91: Dolores | B91: 2026 | C91: 6 | D91: Junio | E91: 975 ml | F91: Sí
A92: Dolores | B92: 2026 | C92: 7 | D92: Julio | E92: 975 ml | F92: Sí
A93: Dolores | B93: 2026 | C93: 8 | D93: Agosto | E93: 975 ml | F93: Sí
A94: Dolores | B94: 2026 | C94: 9 | D94: Septiembre | E94: 975 ml | F94: Sí
A95: Dolores | B95: 2026 | C95: 10 | D95: Octubre | E95: 975 ml | F95: Sí
A96: Dolores | B96: 2026 | C96: 11 | D96: Noviembre | E96: 975 ml | F96: Sí
A97: Dolores | B97: 2026 | C97: 12 | D97: Diciembre | E97: 975 ml | F97: Sí

Sheet Tabla_Escenarios
A1: TABLA DE ESCENARIOS DINÁMICA - SEGÚN SUCURSAL/AÑO/MES ELEGIDOS EN DASHBOARD
A3: Sucursal | B3: =Dashboard!A4 -> Casa Central
A4: Año | B4: =Dashboard!E4 -> 2026
A5: Mes | B5: =Dashboard!A4 -> Casa Central
A6: Base bultos | B6: =SUM(Dashboard!C17:C28) -> 1008980.5
A7: Base HL | B7: =SUM(Dashboard!E17:E28) -> 94090.7
A10: Escenario venta | B10: Bultos ajustados | C10: HL ajustados | D10: Pallets vacíos ajustados | E10: HH totales requeridas | F10: Operarios disponibles netos | G10: Operarios requeridos | H10: Gap operarios | I10: Autoelevadores requeridos | J10: Decisión
A11: -0.3 | B11: =B$6*(1+A11) -> 706286.35 | C11: =B$7*(1+A11) -> 65863.49 | D11: =SUM(Dashboard!B17:B28)*(1+A11) -> 642078.5 | E11: =B11/Parametros!$B$6+C11/Parametros!$B$7+D11/Parametros!$B$8 -> 146321.27 | F11: =AVERAGE(Dashboard!G17:G28) -> 8.0833333 | G11: =E11/Parametros!$B$9 -> 836.12154 | H11: =F11-G11 -> -828.03821 | I11: =ROUNDUP((C11/Parametros!$B$7)/Parametros!$B$10,0) -> 10 | J11: =IF(H11<0,"Agregar "&ROUNDUP(ABS(H11),0)&" operario(s)","Sin acción") -> Agregar 829 operario(s)
A12: -0.25 | B12: =B$6*(1+A12) -> 756735.38 | C12: =B$7*(1+A12) -> 70568.025 | D12: =SUM(Dashboard!B17:B28)*(1+A12) -> 687941.25 | E12: =B12/Parametros!$B$6+C12/Parametros!$B$7+D12/Parametros!$B$8 -> 156772.79 | F12: =AVERAGE(Dashboard!G17:G28) -> 8.0833333 | G12: =E12/Parametros!$B$9 -> 895.84451 | H12: =F12-G12 -> -887.76118 | I12: =ROUNDUP((C12/Parametros!$B$7)/Parametros!$B$10,0) -> 11 | J12: =IF(H12<0,"Agregar "&ROUNDUP(ABS(H12),0)&" operario(s)","Sin acción") -> Agregar 888 operario(s)
A13: -0.2 | B13: =B$6*(1+A13) -> 807184.4 | C13: =B$7*(1+A13) -> 75272.56 | D13: =SUM(Dashboard!B17:B28)*(1+A13) -> 733804 | E13: =B13/Parametros!$B$6+C13/Parametros!$B$7+D13/Parametros!$B$8 -> 167224.31 | F13: =AVERAGE(Dashboard!G17:G28) -> 8.0833333 | G13: =E13/Parametros!$B$9 -> 955.56748 | H13: =F13-G13 -> -947.48415 | I13: =ROUNDUP((C13/Parametros!$B$7)/Parametros!$B$10,0) -> 12 | J13: =IF(H13<0,"Agregar "&ROUNDUP(ABS(H13),0)&" operario(s)","Sin acción") -> Agregar 948 operario(s)
A14: -0.15 | B14: =B$6*(1+A14) -> 857633.43 | C14: =B$7*(1+A14) -> 79977.095 | D14: =SUM(Dashboard!B17:B28)*(1+A14) -> 779666.75 | E14: =B14/Parametros!$B$6+C14/Parametros!$B$7+D14/Parametros!$B$8 -> 177675.83 | F14: =AVERAGE(Dashboard!G17:G28) -> 8.0833333 | G14: =E14/Parametros!$B$9 -> 1015.2904 | H14: =F14-G14 -> -1007.2071 | I14: =ROUNDUP((C14/Parametros!$B$7)/Parametros!$B$10,0) -> 13 | J14: =IF(H14<0,"Agregar "&ROUNDUP(ABS(H14),0)&" operario(s)","Sin acción") -> Agregar 1008 operario(s)
A15: -0.1 | B15: =B$6*(1+A15) -> 908082.45 | C15: =B$7*(1+A15) -> 84681.63 | D15: =SUM(Dashboard!B17:B28)*(1+A15) -> 825529.5 | E15: =B15/Parametros!$B$6+C15/Parametros!$B$7+D15/Parametros!$B$8 -> 188127.35 | F15: =AVERAGE(Dashboard!G17:G28) -> 8.0833333 | G15: =E15/Parametros!$B$9 -> 1075.0134 | H15: =F15-G15 -> -1066.9301 | I15: =ROUNDUP((C15/Parametros!$B$7)/Parametros!$B$10,0) -> 13 | J15: =IF(H15<0,"Agregar "&ROUNDUP(ABS(H15),0)&" operario(s)","Sin acción") -> Agregar 1067 operario(s)
A16: -0.05 | B16: =B$6*(1+A16) -> 958531.48 | C16: =B$7*(1+A16) -> 89386.165 | D16: =SUM(Dashboard!B17:B28)*(1+A16) -> 871392.25 | E16: =B16/Parametros!$B$6+C16/Parametros!$B$7+D16/Parametros!$B$8 -> 198578.87 | F16: =AVERAGE(Dashboard!G17:G28) -> 8.0833333 | G16: =E16/Parametros!$B$9 -> 1134.7364 | H16: =F16-G16 -> -1126.653 | I16: =ROUNDUP((C16/Parametros!$B$7)/Parametros!$B$10,0) -> 14 | J16: =IF(H16<0,"Agregar "&ROUNDUP(ABS(H16),0)&" operario(s)","Sin acción") -> Agregar 1127 operario(s)
A17: 0 | B17: =B$6*(1+A17) -> 1008980.5 | C17: =B$7*(1+A17) -> 94090.7 | D17: =SUM(Dashboard!B17:B28)*(1+A17) -> 917255 | E17: =B17/Parametros!$B$6+C17/Parametros!$B$7+D17/Parametros!$B$8 -> 209030.39 | F17: =AVERAGE(Dashboard!G17:G28) -> 8.0833333 | G17: =E17/Parametros!$B$9 -> 1194.4593 | H17: =F17-G17 -> -1186.376 | I17: =ROUNDUP((C17/Parametros!$B$7)/Parametros!$B$10,0) -> 15 | J17: =IF(H17<0,"Agregar "&ROUNDUP(ABS(H17),0)&" operario(s)","Sin acción") -> Agregar 1187 operario(s)
A18: 0.05 | B18: =B$6*(1+A18) -> 1059429.5 | C18: =B$7*(1+A18) -> 98795.235 | D18: =SUM(Dashboard!B17:B28)*(1+A18) -> 963117.75 | E18: =B18/Parametros!$B$6+C18/Parametros!$B$7+D18/Parametros!$B$8 -> 219481.91 | F18: =AVERAGE(Dashboard!G17:G28) -> 8.0833333 | G18: =E18/Parametros!$B$9 -> 1254.1823 | H18: =F18-G18 -> -1246.099 | I18: =ROUNDUP((C18/Parametros!$B$7)/Parametros!$B$10,0) -> 15 | J18: =IF(H18<0,"Agregar "&ROUNDUP(ABS(H18),0)&" operario(s)","Sin acción") -> Agregar 1247 operario(s)
A19: 0.1 | B19: =B$6*(1+A19) -> 1109878.6 | C19: =B$7*(1+A19) -> 103499.77 | D19: =SUM(Dashboard!B17:B28)*(1+A19) -> 1008980.5 | E19: =B19/Parametros!$B$6+C19/Parametros!$B$7+D19/Parametros!$B$8 -> 229933.42 | F19: =AVERAGE(Dashboard!G17:G28) -> 8.0833333 | G19: =E19/Parametros!$B$9 -> 1313.9053 | H19: =F19-G19 -> -1305.822 | I19: =ROUNDUP((C19/Parametros!$B$7)/Parametros!$B$10,0) -> 16 | J19: =IF(H19<0,"Agregar "&ROUNDUP(ABS(H19),0)&" operario(s)","Sin acción") -> Agregar 1306 operario(s)
A20: 0.15 | B20: =B$6*(1+A20) -> 1160327.6 | C20: =B$7*(1+A20) -> 108204.31 | D20: =SUM(Dashboard!B17:B28)*(1+A20) -> 1054843.2 | E20: =B20/Parametros!$B$6+C20/Parametros!$B$7+D20/Parametros!$B$8 -> 240384.94 | F20: =AVERAGE(Dashboard!G17:G28) -> 8.0833333 | G20: =E20/Parametros!$B$9 -> 1373.6283 | H20: =F20-G20 -> -1365.5449 | I20: =ROUNDUP((C20/Parametros!$B$7)/Parametros!$B$10,0) -> 17 | J20: =IF(H20<0,"Agregar "&ROUNDUP(ABS(H20),0)&" operario(s)","Sin acción") -> Agregar 1366 operario(s)
A21: 0.2 | B21: =B$6*(1+A21) -> 1210776.6 | C21: =B$7*(1+A21) -> 112908.84 | D21: =SUM(Dashboard!B17:B28)*(1+A21) -> 1100706 | E21: =B21/Parametros!$B$6+C21/Parametros!$B$7+D21/Parametros!$B$8 -> 250836.46 | F21: =AVERAGE(Dashboard!G17:G28) -> 8.0833333 | G21: =E21/Parametros!$B$9 -> 1433.3512 | H21: =F21-G21 -> -1425.2679 | I21: =ROUNDUP((C21/Parametros!$B$7)/Parametros!$B$10,0) -> 18 | J21: =IF(H21<0,"Agregar "&ROUNDUP(ABS(H21),0)&" operario(s)","Sin acción") -> Agregar 1426 operario(s)
A22: 0.25 | B22: =B$6*(1+A22) -> 1261225.6 | C22: =B$7*(1+A22) -> 117613.38 | D22: =SUM(Dashboard!B17:B28)*(1+A22) -> 1146568.8 | E22: =B22/Parametros!$B$6+C22/Parametros!$B$7+D22/Parametros!$B$8 -> 261287.98 | F22: =AVERAGE(Dashboard!G17:G28) -> 8.0833333 | G22: =E22/Parametros!$B$9 -> 1493.0742 | H22: =F22-G22 -> -1484.9909 | I22: =ROUNDUP((C22/Parametros!$B$7)/Parametros!$B$10,0) -> 18 | J22: =IF(H22<0,"Agregar "&ROUNDUP(ABS(H22),0)&" operario(s)","Sin acción") -> Agregar 1485 operario(s)
A23: 0.3 | B23: =B$6*(1+A23) -> 1311674.7 | C23: =B$7*(1+A23) -> 122317.91 | D23: =SUM(Dashboard!B17:B28)*(1+A23) -> 1192431.5 | E23: =B23/Parametros!$B$6+C23/Parametros!$B$7+D23/Parametros!$B$8 -> 271739.5 | F23: =AVERAGE(Dashboard!G17:G28) -> 8.0833333 | G23: =E23/Parametros!$B$9 -> 1552.7972 | H23: =F23-G23 -> -1544.7138 | I23: =ROUNDUP((C23/Parametros!$B$7)/Parametros!$B$10,0) -> 19 | J23: =IF(H23<0,"Agregar "&ROUNDUP(ABS(H23),0)&" operario(s)","Sin acción") -> Agregar 1545 operario(s)

Sheet SOP_y_Comentario
A1: SOP - Simulador Integral de Capacidad de Almacén
A3: Objetivo
A4: Dimensionar mensualmente la capacidad de Casa Central y Dolores, cruzando volumen proyectado, escenario de venta, productividad objetivo, ausentismo, dotación planificada y disponibilidad de autoelevadores.
A6: Proceso
A7: 1. Actualizar mensualmente los datos base de volumen, pallets y dotación.
A8: 2. Seleccionar sucursal, año, mes y escenario de venta en el Dashboard.
A9: 3. Validar el resultado: HH requeridas, operarios requeridos, operarios disponibles, gap y MHE.
A10: 4. Si hay gap negativo, definir acción: contratación eventual, horas extra, reasignación o alquiler adicional.
A11: 5. Revisar en rutina mensual y conservar evidencia de decisiones.
A13: Comentario DPO sugerido
A14: La unidad cuenta con un simulador integral de capacidad de almacén que permite evaluar Casa Central y Dolores por separado. La herramienta considera volumen de bultos y HL, clasificación de vacíos, productividad objetivo, ausentismo, dotación planificada y disponibilidad de autoelevadores. Mediante un selector de escenarios de venta de -30% a +30%, el simulador recalcula automáticamente HH requeridas, operarios necesarios, MHE requeridos y brechas operativas, permitiendo anticipar necesidades de recursos y definir planes de acción.
